{
 "spdxVersion": "SPDX-2.3",
 "dataLicense": "CC0-1.0",
 "SPDXID": "SPDXRef-DOCUMENT",
 "name": "portainer/portainer-k8s-beta@sha256:60d102b37d8f7f40c92fda061687bbe09fd6c64cfd6b9b1dd265e125199a2dea",
 "documentNamespace": "https://anchore.com/syft/image/portainer/portainer-k8s-beta@sha256-60d102b37d8f7f40c92fda061687bbe09fd6c64cfd6b9b1dd265e125199a2dea-f8a293b8-2d2e-4cda-a15a-419725a9cddf",
 "creationInfo": {
  "licenseListVersion": "3.19",
  "creators": [
   "Organization: Anchore, Inc",
   "Tool: syft-0.64.0"
  ],
  "created": "2022-12-29T17:57:13Z",
  "comment": ""
 },
 "packages": [
  {
   "name": "github.com/alecthomas/template",
   "SPDXID": "SPDXRef-Package-go-module-github.com-alecthomas-template-7fd133dfb3030377",
   "versionInfo": "v0.0.0-20160405071501-a0175ee3bccc",
   "downloadLocation": "NOASSERTION",
   "checksums": [
    {
     "algorithm": "SHA256",
     "checksumValue": "7002837d6879569760321268b1f2679f9fc5a0dd92459e29edf24d5f9f183da5"
    }
   ],
   "sourceInfo": "acquired package info from go module information: /portainer",
   "licenseConcluded": "NONE",
   "licenseDeclared": "NONE",
   "copyrightText": "NOASSERTION",
   "externalRefs": [
    {
     "referenceCategory": "SECURITY",
     "referenceType": "cpe23Type",
     "referenceLocator": "cpe:2.3:a:alecthomas:template:v0.0.0-20160405071501-a0175ee3bccc:*:*:*:*:*:*:*",
     "comment": ""
    },
    {
     "referenceCategory": "PACKAGE-MANAGER",
     "referenceType": "purl",
     "referenceLocator": "pkg:golang/github.com/alecthomas/template@v0.0.0-20160405071501-a0175ee3bccc",
     "comment": ""
    }
   ]
  },
  {
   "name": "github.com/alecthomas/units",
   "SPDXID": "SPDXRef-Package-go-module-github.com-alecthomas-units-19b142f409cad419",
   "versionInfo": "v0.0.0-20151022065526-2efee857e7cf",
   "downloadLocation": "NOASSERTION",
   "checksums": [
    {
     "algorithm": "SHA256",
     "checksumValue": "a9eb7540d7d7b10c5366a2c6e2813ada6273c0f201f3e4de7b844d08bf6e96b6"
    }
   ],
   "sourceInfo": "acquired package info from go module information: /portainer",
   "licenseConcluded": "NONE",
   "licenseDeclared": "NONE",
   "copyrightText": "NOASSERTION",
   "externalRefs": [
    {
     "referenceCategory": "SECURITY",
     "referenceType": "cpe23Type",
     "referenceLocator": "cpe:2.3:a:alecthomas:units:v0.0.0-20151022065526-2efee857e7cf:*:*:*:*:*:*:*",
     "comment": ""
    },
    {
     "referenceCategory": "PACKAGE-MANAGER",
     "referenceType": "purl",
     "referenceLocator": "pkg:golang/github.com/alecthomas/units@v0.0.0-20151022065526-2efee857e7cf",
     "comment": ""
    }
   ]
  },
  {
   "name": "github.com/andrew-d/go-termutil",
   "SPDXID": "SPDXRef-Package-go-module-github.com-andrew-d-go-termutil-137bb0481b731035",
   "versionInfo": "v0.0.0-20150726205930-009166a695a2",
   "downloadLocation": "NOASSERTION",
   "checksums": [
    {
     "algorithm": "SHA256",
     "checksumValue": "6b10620b9d1c3593acef2807e41810a7837e698ad9d83369599d4a1b754e48e3"
    }
   ],
   "sourceInfo": "acquired package info from go module information: /portainer",
   "licenseConcluded": "NONE",
   "licenseDeclared": "NONE",
   "copyrightText": "NOASSERTION",
   "externalRefs": [
    {
     "referenceCategory": "SECURITY",
     "referenceType": "cpe23Type",
     "referenceLocator": "cpe:2.3:a:andrew-d:go-termutil:v0.0.0-20150726205930-009166a695a2:*:*:*:*:*:*:*",
     "comment": ""
    },
    {
     "referenceCategory": "SECURITY",
     "referenceType": "cpe23Type",
     "referenceLocator": "cpe:2.3:a:andrew-d:go_termutil:v0.0.0-20150726205930-009166a695a2:*:*:*:*:*:*:*",
     "comment": ""
    },
    {
     "referenceCategory": "SECURITY",
     "referenceType": "cpe23Type",
     "referenceLocator": "cpe:2.3:a:andrew_d:go-termutil:v0.0.0-20150726205930-009166a695a2:*:*:*:*:*:*:*",
     "comment": ""
    },
    {
     "referenceCategory": "SECURITY",
     "referenceType": "cpe23Type",
     "referenceLocator": "cpe:2.3:a:andrew_d:go_termutil:v0.0.0-20150726205930-009166a695a2:*:*:*:*:*:*:*",
     "comment": ""
    },
    {
     "referenceCategory": "SECURITY",
     "referenceType": "cpe23Type",
     "referenceLocator": "cpe:2.3:a:andrew:go-termutil:v0.0.0-20150726205930-009166a695a2:*:*:*:*:*:*:*",
     "comment": ""
    },
    {
     "referenceCategory": "SECURITY",
     "referenceType": "cpe23Type",
     "referenceLocator": "cpe:2.3:a:andrew:go_termutil:v0.0.0-20150726205930-009166a695a2:*:*:*:*:*:*:*",
     "comment": ""
    },
    {
     "referenceCategory": "PACKAGE-MANAGER",
     "referenceType": "purl",
     "referenceLocator": "pkg:golang/github.com/andrew-d/go-termutil@v0.0.0-20150726205930-009166a695a2",
     "comment": ""
    }
   ]
  },
  {
   "name": "github.com/armon/go-socks5",
   "SPDXID": "SPDXRef-Package-go-module-github.com-armon-go-socks5-b9ebb49469b28acb",
   "versionInfo": "v0.0.0-20160902184237-e75332964ef5",
   "downloadLocation": "NOASSERTION",
   "checksums": [
    {
     "algorithm": "SHA256",
     "checksumValue": "d02c193596f1a7af521cf74f24037f859226d02e0e22d764942166311598a62a"
    }
   ],
   "sourceInfo": "acquired package info from go module information: /portainer",
   "licenseConcluded": "NONE",
   "licenseDeclared": "NONE",
   "copyrightText": "NOASSERTION",
   "externalRefs": [
    {
     "referenceCategory": "SECURITY",
     "referenceType": "cpe23Type",
     "referenceLocator": "cpe:2.3:a:armon:go-socks5:v0.0.0-20160902184237-e75332964ef5:*:*:*:*:*:*:*",
     "comment": ""
    },
    {
     "referenceCategory": "SECURITY",
     "referenceType": "cpe23Type",
     "referenceLocator": "cpe:2.3:a:armon:go_socks5:v0.0.0-20160902184237-e75332964ef5:*:*:*:*:*:*:*",
     "comment": ""
    },
    {
     "referenceCategory": "PACKAGE-MANAGER",
     "referenceType": "purl",
     "referenceLocator": "pkg:golang/github.com/armon/go-socks5@v0.0.0-20160902184237-e75332964ef5",
     "comment": ""
    }
   ]
  },
  {
   "name": "github.com/asaskevich/govalidator",
   "SPDXID": "SPDXRef-Package-go-module-github.com-asaskevich-govalidator-651fc8d9b8916f0d",
   "versionInfo": "v0.0.0-20190424111038-f61b66f89f4a",
   "downloadLocation": "NOASSERTION",
   "checksums": [
    {
     "algorithm": "SHA256",
     "checksumValue": "89d9fbd7c43807a006bbf8794b17bae8761576a746bb697d21e6ea862fc01280"
    }
   ],
   "sourceInfo": "acquired package info from go module information: /portainer",
   "licenseConcluded": "NONE",
   "licenseDeclared": "NONE",
   "copyrightText": "NOASSERTION",
   "externalRefs": [
    {
     "referenceCategory": "SECURITY",
     "referenceType": "cpe23Type",
     "referenceLocator": "cpe:2.3:a:asaskevich:govalidator:v0.0.0-20190424111038-f61b66f89f4a:*:*:*:*:*:*:*",
     "comment": ""
    },
    {
     "referenceCategory": "PACKAGE-MANAGER",
     "referenceType": "purl",
     "referenceLocator": "pkg:golang/github.com/asaskevich/govalidator@v0.0.0-20190424111038-f61b66f89f4a",
     "comment": ""
    }
   ]
  },
  {
   "name": "github.com/beorn7/perks",
   "SPDXID": "SPDXRef-Package-go-module-github.com-beorn7-perks-1012eb1d80966f56",
   "versionInfo": "v1.0.1",
   "downloadLocation": "NOASSERTION",
   "checksums": [
    {
     "algorithm": "SHA256",
     "checksumValue": "5656ca2a735f57c6c9cdeaa86b870e2aa3ba6d8af75a0299c4ef19d7afa1b0e3"
    }
   ],
   "sourceInfo": "acquired package info from go module information: /portainer",
   "licenseConcluded": "NONE",
   "licenseDeclared": "NONE",
   "copyrightText": "NOASSERTION",
   "externalRefs": [
    {
     "referenceCategory": "SECURITY",
     "referenceType": "cpe23Type",
     "referenceLocator": "cpe:2.3:a:beorn7:perks:v1.0.1:*:*:*:*:*:*:*",
     "comment": ""
    },
    {
     "referenceCategory": "PACKAGE-MANAGER",
     "referenceType": "purl",
     "referenceLocator": "pkg:golang/github.com/beorn7/perks@v1.0.1",
     "comment": ""
    }
   ]
  },
  {
   "name": "github.com/boltdb/bolt",
   "SPDXID": "SPDXRef-Package-go-module-github.com-boltdb-bolt-7718be96be05a406",
   "versionInfo": "v1.3.1",
   "downloadLocation": "NOASSERTION",
   "checksums": [
    {
     "algorithm": "SHA256",
     "checksumValue": "2509b23f8641adc7be650bb4758ebad0531f6adba66032ee9fd841094548905e"
    }
   ],
   "sourceInfo": "acquired package info from go module information: /portainer",
   "licenseConcluded": "NONE",
   "licenseDeclared": "NONE",
   "copyrightText": "NOASSERTION",
   "externalRefs": [
    {
     "referenceCategory": "SECURITY",
     "referenceType": "cpe23Type",
     "referenceLocator": "cpe:2.3:a:boltdb:bolt:v1.3.1:*:*:*:*:*:*:*",
     "comment": ""
    },
    {
     "referenceCategory": "PACKAGE-MANAGER",
     "referenceType": "purl",
     "referenceLocator": "pkg:golang/github.com/boltdb/bolt@v1.3.1",
     "comment": ""
    }
   ]
  },
  {
   "name": "github.com/containerd/containerd",
   "SPDXID": "SPDXRef-Package-go-module-github.com-containerd-containerd-32aca7af2fa936da",
   "versionInfo": "v1.3.1",
   "downloadLocation": "NOASSERTION",
   "checksums": [
    {
     "algorithm": "SHA256",
     "checksumValue": "2dd6d6c4b864008c463bb8779804c79326afd3a5ae0ecff24d6c4896324e4e4b"
    }
   ],
   "sourceInfo": "acquired package info from go module information: /portainer",
   "licenseConcluded": "NONE",
   "licenseDeclared": "NONE",
   "copyrightText": "NOASSERTION",
   "externalRefs": [
    {
     "referenceCategory": "SECURITY",
     "referenceType": "cpe23Type",
     "referenceLocator": "cpe:2.3:a:containerd:containerd:v1.3.1:*:*:*:*:*:*:*",
     "comment": ""
    },
    {
     "referenceCategory": "PACKAGE-MANAGER",
     "referenceType": "purl",
     "referenceLocator": "pkg:golang/github.com/containerd/containerd@v1.3.1",
     "comment": ""
    }
   ]
  },
  {
   "name": "github.com/containerd/continuity",
   "SPDXID": "SPDXRef-Package-go-module-github.com-containerd-continuity-45555a3716bffaeb",
   "versionInfo": "v0.0.0-20190426062206-aaeac12a7ffc",
   "downloadLocation": "NOASSERTION",
   "checksums": [
    {
     "algorithm": "SHA256",
     "checksumValue": "4cffb9df8c1595feb5b26108ab59f02cb02341510ad84003a16dc25fd02e4fef"
    }
   ],
   "sourceInfo": "acquired package info from go module information: /portainer",
   "licenseConcluded": "NONE",
   "licenseDeclared": "NONE",
   "copyrightText": "NOASSERTION",
   "externalRefs": [
    {
     "referenceCategory": "SECURITY",
     "referenceType": "cpe23Type",
     "referenceLocator": "cpe:2.3:a:containerd:continuity:v0.0.0-20190426062206-aaeac12a7ffc:*:*:*:*:*:*:*",
     "comment": ""
    },
    {
     "referenceCategory": "PACKAGE-MANAGER",
     "referenceType": "purl",
     "referenceLocator": "pkg:golang/github.com/containerd/continuity@v0.0.0-20190426062206-aaeac12a7ffc",
     "comment": ""
    }
   ]
  },
  {
   "name": "github.com/coreos/go-semver",
   "SPDXID": "SPDXRef-Package-go-module-github.com-coreos-go-semver-6160a79e8893b8fd",
   "versionInfo": "v0.3.0",
   "downloadLocation": "NOASSERTION",
   "checksums": [
    {
     "algorithm": "SHA256",
     "checksumValue": "c241cb8b0d163404d99d21bb7a92ecba388c0a03c073dc618c9e2d82703199f3"
    }
   ],
   "sourceInfo": "acquired package info from go module information: /portainer",
   "licenseConcluded": "NONE",
   "licenseDeclared": "NONE",
   "copyrightText": "NOASSERTION",
   "externalRefs": [
    {
     "referenceCategory": "SECURITY",
     "referenceType": "cpe23Type",
     "referenceLocator": "cpe:2.3:a:coreos:go-semver:v0.3.0:*:*:*:*:*:*:*",
     "comment": ""
    },
    {
     "referenceCategory": "SECURITY",
     "referenceType": "cpe23Type",
     "referenceLocator": "cpe:2.3:a:coreos:go_semver:v0.3.0:*:*:*:*:*:*:*",
     "comment": ""
    },
    {
     "referenceCategory": "PACKAGE-MANAGER",
     "referenceType": "purl",
     "referenceLocator": "pkg:golang/github.com/coreos/go-semver@v0.3.0",
     "comment": ""
    }
   ]
  },
  {
   "name": "github.com/davecgh/go-spew",
   "SPDXID": "SPDXRef-Package-go-module-github.com-davecgh-go-spew-540810490eb797d",
   "versionInfo": "v1.1.1",
   "downloadLocation": "NOASSERTION",
   "checksums": [
    {
     "algorithm": "SHA256",
     "checksumValue": "be3f63feed5baa7bc211f24ec1486d94e011aacdfeae41d8635de36164d4f7b7"
    }
   ],
   "sourceInfo": "acquired package info from go module information: /portainer",
   "licenseConcluded": "NONE",
   "licenseDeclared": "NONE",
   "copyrightText": "NOASSERTION",
   "externalRefs": [
    {
     "referenceCategory": "SECURITY",
     "referenceType": "cpe23Type",
     "referenceLocator": "cpe:2.3:a:davecgh:go-spew:v1.1.1:*:*:*:*:*:*:*",
     "comment": ""
    },
    {
     "referenceCategory": "SECURITY",
     "referenceType": "cpe23Type",
     "referenceLocator": "cpe:2.3:a:davecgh:go_spew:v1.1.1:*:*:*:*:*:*:*",
     "comment": ""
    },
    {
     "referenceCategory": "PACKAGE-MANAGER",
     "referenceType": "purl",
     "referenceLocator": "pkg:golang/github.com/davecgh/go-spew@v1.1.1",
     "comment": ""
    }
   ]
  },
  {
   "name": "github.com/dchest/uniuri",
   "SPDXID": "SPDXRef-Package-go-module-github.com-dchest-uniuri-f0993d624671a852",
   "versionInfo": "v0.0.0-20160212164326-8902c56451e9",
   "downloadLocation": "NOASSERTION",
   "checksums": [
    {
     "algorithm": "SHA256",
     "checksumValue": "ef894b351cefb1d22591381f0d232e68f8c1af871fea4ee9c10400366ff22ca5"
    }
   ],
   "sourceInfo": "acquired package info from go module information: /portainer",
   "licenseConcluded": "NONE",
   "licenseDeclared": "NONE",
   "copyrightText": "NOASSERTION",
   "externalRefs": [
    {
     "referenceCategory": "SECURITY",
     "referenceType": "cpe23Type",
     "referenceLocator": "cpe:2.3:a:dchest:uniuri:v0.0.0-20160212164326-8902c56451e9:*:*:*:*:*:*:*",
     "comment": ""
    },
    {
     "referenceCategory": "PACKAGE-MANAGER",
     "referenceType": "purl",
     "referenceLocator": "pkg:golang/github.com/dchest/uniuri@v0.0.0-20160212164326-8902c56451e9",
     "comment": ""
    }
   ]
  },
  {
   "name": "github.com/dgrijalva/jwt-go",
   "SPDXID": "SPDXRef-Package-go-module-github.com-dgrijalva-jwt-go-972056d5ed59a7a6",
   "versionInfo": "v3.2.0+incompatible",
   "downloadLocation": "NOASSERTION",
   "checksums": [
    {
     "algorithm": "SHA256",
     "checksumValue": "eea94e1a58842995d30e0e8e4e37e804a0d75abba608032997f4c5438ff990b3"
    }
   ],
   "sourceInfo": "acquired package info from go module information: /portainer",
   "licenseConcluded": "NONE",
   "licenseDeclared": "NONE",
   "copyrightText": "NOASSERTION",
   "externalRefs": [
    {
     "referenceCategory": "SECURITY",
     "referenceType": "cpe23Type",
     "referenceLocator": "cpe:2.3:a:dgrijalva:jwt-go:v3.2.0\\+incompatible:*:*:*:*:*:*:*",
     "comment": ""
    },
    {
     "referenceCategory": "SECURITY",
     "referenceType": "cpe23Type",
     "referenceLocator": "cpe:2.3:a:dgrijalva:jwt_go:v3.2.0\\+incompatible:*:*:*:*:*:*:*",
     "comment": ""
    },
    {
     "referenceCategory": "PACKAGE-MANAGER",
     "referenceType": "purl",
     "referenceLocator": "pkg:golang/github.com/dgrijalva/jwt-go@v3.2.0+incompatible",
     "comment": ""
    }
   ]
  },
  {
   "name": "github.com/docker/cli",
   "SPDXID": "SPDXRef-Package-go-module-github.com-docker-cli-e85ba818d0b7a506",
   "versionInfo": "v0.0.0-20191126203649-54d085b857e9",
   "downloadLocation": "NOASSERTION",
   "checksums": [
    {
     "algorithm": "SHA256",
     "checksumValue": "43a0fa6f68912a1bed2f75a3f69d12c8f3af50327586deb699b881a0d27702eb"
    }
   ],
   "sourceInfo": "acquired package info from go module information: /portainer",
   "licenseConcluded": "NONE",
   "licenseDeclared": "NONE",
   "copyrightText": "NOASSERTION",
   "externalRefs": [
    {
     "referenceCategory": "SECURITY",
     "referenceType": "cpe23Type",
     "referenceLocator": "cpe:2.3:a:docker:cli:v0.0.0-20191126203649-54d085b857e9:*:*:*:*:*:*:*",
     "comment": ""
    },
    {
     "referenceCategory": "PACKAGE-MANAGER",
     "referenceType": "purl",
     "referenceLocator": "pkg:golang/github.com/docker/cli@v0.0.0-20191126203649-54d085b857e9",
     "comment": ""
    }
   ]
  },
  {
   "name": "github.com/docker/distribution",
   "SPDXID": "SPDXRef-Package-go-module-github.com-docker-distribution-1091daf066216c63",
   "versionInfo": "v2.7.1+incompatible",
   "downloadLocation": "NOASSERTION",
   "checksums": [
    {
     "algorithm": "SHA256",
     "checksumValue": "6b99a5915ced87a5b90387ceb12dc3d843b90549ac269701f9c4652d4edc4ae8"
    }
   ],
   "sourceInfo": "acquired package info from go module information: /portainer",
   "licenseConcluded": "NONE",
   "licenseDeclared": "NONE",
   "copyrightText": "NOASSERTION",
   "externalRefs": [
    {
     "referenceCategory": "SECURITY",
     "referenceType": "cpe23Type",
     "referenceLocator": "cpe:2.3:a:docker:distribution:v2.7.1\\+incompatible:*:*:*:*:*:*:*",
     "comment": ""
    },
    {
     "referenceCategory": "PACKAGE-MANAGER",
     "referenceType": "purl",
     "referenceLocator": "pkg:golang/github.com/docker/distribution@v2.7.1+incompatible",
     "comment": ""
    }
   ]
  },
  {
   "name": "github.com/docker/docker-credential-helpers",
   "SPDXID": "SPDXRef-Package-go-module-github.com-docker-docker-credential-helpers-5921810349e8d83f",
   "versionInfo": "v0.6.3",
   "downloadLocation": "NOASSERTION",
   "checksums": [
    {
     "algorithm": "SHA256",
     "checksumValue": "cc8da9f7ed4d4187671bab0c536e845f86951a5a9b227490c505cbbf327844f4"
    }
   ],
   "sourceInfo": "acquired package info from go module information: /portainer",
   "licenseConcluded": "NONE",
   "licenseDeclared": "NONE",
   "copyrightText": "NOASSERTION",
   "externalRefs": [
    {
     "referenceCategory": "SECURITY",
     "referenceType": "cpe23Type",
     "referenceLocator": "cpe:2.3:a:docker:docker-credential-helpers:v0.6.3:*:*:*:*:*:*:*",
     "comment": ""
    },
    {
     "referenceCategory": "SECURITY",
     "referenceType": "cpe23Type",
     "referenceLocator": "cpe:2.3:a:docker:docker_credential_helpers:v0.6.3:*:*:*:*:*:*:*",
     "comment": ""
    },
    {
     "referenceCategory": "PACKAGE-MANAGER",
     "referenceType": "purl",
     "referenceLocator": "pkg:golang/github.com/docker/docker-credential-helpers@v0.6.3",
     "comment": ""
    }
   ]
  },
  {
   "name": "github.com/docker/engine",
   "SPDXID": "SPDXRef-Package-go-module-github.com-docker-engine-5d7d2d6eecfe54ac",
   "versionInfo": "v1.4.2-0.20191127222017-3152f9436292",
   "downloadLocation": "NOASSERTION",
   "checksums": [
    {
     "algorithm": "SHA256",
     "checksumValue": "a90ee6c3e0955a9463e435812f80951ed05b1907653c28f88f57af0e1d1eb61c"
    }
   ],
   "sourceInfo": "acquired package info from go module information: /portainer",
   "licenseConcluded": "NONE",
   "licenseDeclared": "NONE",
   "copyrightText": "NOASSERTION",
   "externalRefs": [
    {
     "referenceCategory": "SECURITY",
     "referenceType": "cpe23Type",
     "referenceLocator": "cpe:2.3:a:docker:engine:v1.4.2-0.20191127222017-3152f9436292:*:*:*:*:*:*:*",
     "comment": ""
    },
    {
     "referenceCategory": "PACKAGE-MANAGER",
     "referenceType": "purl",
     "referenceLocator": "pkg:golang/github.com/docker/engine@v1.4.2-0.20191127222017-3152f9436292",
     "comment": ""
    }
   ]
  },
  {
   "name": "github.com/docker/go-connections",
   "SPDXID": "SPDXRef-Package-go-module-github.com-docker-go-connections-143945ce6d1acc00",
   "versionInfo": "v0.3.0",
   "downloadLocation": "NOASSERTION",
   "checksums": [
    {
     "algorithm": "SHA256",
     "checksumValue": "de53a733d712ce01b0c7c55f2bf346396e5f2d0d068c894291a92d17e9f533aa"
    }
   ],
   "sourceInfo": "acquired package info from go module information: /portainer",
   "licenseConcluded": "NONE",
   "licenseDeclared": "NONE",
   "copyrightText": "NOASSERTION",
   "externalRefs": [
    {
     "referenceCategory": "SECURITY",
     "referenceType": "cpe23Type",
     "referenceLocator": "cpe:2.3:a:docker:go-connections:v0.3.0:*:*:*:*:*:*:*",
     "comment": ""
    },
    {
     "referenceCategory": "SECURITY",
     "referenceType": "cpe23Type",
     "referenceLocator": "cpe:2.3:a:docker:go_connections:v0.3.0:*:*:*:*:*:*:*",
     "comment": ""
    },
    {
     "referenceCategory": "PACKAGE-MANAGER",
     "referenceType": "purl",
     "referenceLocator": "pkg:golang/github.com/docker/go-connections@v0.3.0",
     "comment": ""
    }
   ]
  },
  {
   "name": "github.com/docker/go-metrics",
   "SPDXID": "SPDXRef-Package-go-module-github.com-docker-go-metrics-1fc009d4d35182b",
   "versionInfo": "v0.0.0-20181218153428-b84716841b82",
   "downloadLocation": "NOASSERTION",
   "checksums": [
    {
     "algorithm": "SHA256",
     "checksumValue": "5f47e3f37eb3c7df7316ef37bff33bf43b819fce082ff4b2c75498e98e5910c0"
    }
   ],
   "sourceInfo": "acquired package info from go module information: /portainer",
   "licenseConcluded": "NONE",
   "licenseDeclared": "NONE",
   "copyrightText": "NOASSERTION",
   "externalRefs": [
    {
     "referenceCategory": "SECURITY",
     "referenceType": "cpe23Type",
     "referenceLocator": "cpe:2.3:a:docker:go-metrics:v0.0.0-20181218153428-b84716841b82:*:*:*:*:*:*:*",
     "comment": ""
    },
    {
     "referenceCategory": "SECURITY",
     "referenceType": "cpe23Type",
     "referenceLocator": "cpe:2.3:a:docker:go_metrics:v0.0.0-20181218153428-b84716841b82:*:*:*:*:*:*:*",
     "comment": ""
    },
    {
     "referenceCategory": "PACKAGE-MANAGER",
     "referenceType": "purl",
     "referenceLocator": "pkg:golang/github.com/docker/go-metrics@v0.0.0-20181218153428-b84716841b82",
     "comment": ""
    }
   ]
  },
  {
   "name": "github.com/docker/go-units",
   "SPDXID": "SPDXRef-Package-go-module-github.com-docker-go-units-b79c1d0349325e5b",
   "versionInfo": "v0.4.0",
   "downloadLocation": "NOASSERTION",
   "checksums": [
    {
     "algorithm": "SHA256",
     "checksumValue": "dee8743e0570b379c803443e3300c2f328c43dff738d17d96565d960372ddd3c"
    }
   ],
   "sourceInfo": "acquired package info from go module information: /portainer",
   "licenseConcluded": "NONE",
   "licenseDeclared": "NONE",
   "copyrightText": "NOASSERTION",
   "externalRefs": [
    {
     "referenceCategory": "SECURITY",
     "referenceType": "cpe23Type",
     "referenceLocator": "cpe:2.3:a:docker:go-units:v0.4.0:*:*:*:*:*:*:*",
     "comment": ""
    },
    {
     "referenceCategory": "SECURITY",
     "referenceType": "cpe23Type",
     "referenceLocator": "cpe:2.3:a:docker:go_units:v0.4.0:*:*:*:*:*:*:*",
     "comment": ""
    },
    {
     "referenceCategory": "PACKAGE-MANAGER",
     "referenceType": "purl",
     "referenceLocator": "pkg:golang/github.com/docker/go-units@v0.4.0",
     "comment": ""
    }
   ]
  },
  {
   "name": "github.com/docker/spdystream",
   "SPDXID": "SPDXRef-Package-go-module-github.com-docker-spdystream-49f89e9321e585d7",
   "versionInfo": "v0.0.0-20160310174837-449fdfce4d96",
   "downloadLocation": "NOASSERTION",
   "checksums": [
    {
     "algorithm": "SHA256",
     "checksumValue": "71e9f0ad2566f99ed02d257f06c9de9c039c0d7757e1c32fe303f407fe506cf8"
    }
   ],
   "sourceInfo": "acquired package info from go module information: /portainer",
   "licenseConcluded": "NONE",
   "licenseDeclared": "NONE",
   "copyrightText": "NOASSERTION",
   "externalRefs": [
    {
     "referenceCategory": "SECURITY",
     "referenceType": "cpe23Type",
     "referenceLocator": "cpe:2.3:a:docker:spdystream:v0.0.0-20160310174837-449fdfce4d96:*:*:*:*:*:*:*",
     "comment": ""
    },
    {
     "referenceCategory": "PACKAGE-MANAGER",
     "referenceType": "purl",
     "referenceLocator": "pkg:golang/github.com/docker/spdystream@v0.0.0-20160310174837-449fdfce4d96",
     "comment": ""
    }
   ]
  },
  {
   "name": "github.com/emirpasic/gods",
   "SPDXID": "SPDXRef-Package-go-module-github.com-emirpasic-gods-f4b2b35db5207646",
   "versionInfo": "v1.12.0",
   "downloadLocation": "NOASSERTION",
   "checksums": [
    {
     "algorithm": "SHA256",
     "checksumValue": "4005083d2682bb81be3ce725c5ea9bdc5f963e974aa851a5c37ebec8ecc696b8"
    }
   ],
   "sourceInfo": "acquired package info from go module information: /portainer",
   "licenseConcluded": "NONE",
   "licenseDeclared": "NONE",
   "copyrightText": "NOASSERTION",
   "externalRefs": [
    {
     "referenceCategory": "SECURITY",
     "referenceType": "cpe23Type",
     "referenceLocator": "cpe:2.3:a:emirpasic:gods:v1.12.0:*:*:*:*:*:*:*",
     "comment": ""
    },
    {
     "referenceCategory": "PACKAGE-MANAGER",
     "referenceType": "purl",
     "referenceLocator": "pkg:golang/github.com/emirpasic/gods@v1.12.0",
     "comment": ""
    }
   ]
  },
  {
   "name": "github.com/flynn/go-shlex",
   "SPDXID": "SPDXRef-Package-go-module-github.com-flynn-go-shlex-c7c3713da468f0d7",
   "versionInfo": "v0.0.0-20150515145356-3f9db97f8568",
   "downloadLocation": "NOASSERTION",
   "checksums": [
    {
     "algorithm": "SHA256",
     "checksumValue": "047b258c7cd59517324218ebb2ce93653758d957c2a993dbbf993788115ad994"
    }
   ],
   "sourceInfo": "acquired package info from go module information: /portainer",
   "licenseConcluded": "NONE",
   "licenseDeclared": "NONE",
   "copyrightText": "NOASSERTION",
   "externalRefs": [
    {
     "referenceCategory": "SECURITY",
     "referenceType": "cpe23Type",
     "referenceLocator": "cpe:2.3:a:flynn:go-shlex:v0.0.0-20150515145356-3f9db97f8568:*:*:*:*:*:*:*",
     "comment": ""
    },
    {
     "referenceCategory": "SECURITY",
     "referenceType": "cpe23Type",
     "referenceLocator": "cpe:2.3:a:flynn:go_shlex:v0.0.0-20150515145356-3f9db97f8568:*:*:*:*:*:*:*",
     "comment": ""
    },
    {
     "referenceCategory": "PACKAGE-MANAGER",
     "referenceType": "purl",
     "referenceLocator": "pkg:golang/github.com/flynn/go-shlex@v0.0.0-20150515145356-3f9db97f8568",
     "comment": ""
    }
   ]
  },
  {
   "name": "github.com/fsnotify/fsnotify",
   "SPDXID": "SPDXRef-Package-go-module-github.com-fsnotify-fsnotify-6e2751535d3b44cd",
   "versionInfo": "v1.4.7",
   "downloadLocation": "NOASSERTION",
   "checksums": [
    {
     "algorithm": "SHA256",
     "checksumValue": "217b3e40b9a75d6d82717b98fbc333bff7d612c3c65b1a9e7cfb423f90a757d2"
    }
   ],
   "sourceInfo": "acquired package info from go module information: /portainer",
   "licenseConcluded": "NONE",
   "licenseDeclared": "NONE",
   "copyrightText": "NOASSERTION",
   "externalRefs": [
    {
     "referenceCategory": "SECURITY",
     "referenceType": "cpe23Type",
     "referenceLocator": "cpe:2.3:a:fsnotify:fsnotify:v1.4.7:*:*:*:*:*:*:*",
     "comment": ""
    },
    {
     "referenceCategory": "PACKAGE-MANAGER",
     "referenceType": "purl",
     "referenceLocator": "pkg:golang/github.com/fsnotify/fsnotify@v1.4.7",
     "comment": ""
    }
   ]
  },
  {
   "name": "github.com/g07cha/defender",
   "SPDXID": "SPDXRef-Package-go-module-github.com-g07cha-defender-f0f9f2d9b4517b74",
   "versionInfo": "v0.0.0-20180505193036-5665c627c814",
   "downloadLocation": "NOASSERTION",
   "checksums": [
    {
     "algorithm": "SHA256",
     "checksumValue": "816be7889e066c57e47fbd349329002266cb884314d10dd037d850dba26cd695"
    }
   ],
   "sourceInfo": "acquired package info from go module information: /portainer",
   "licenseConcluded": "NONE",
   "licenseDeclared": "NONE",
   "copyrightText": "NOASSERTION",
   "externalRefs": [
    {
     "referenceCategory": "SECURITY",
     "referenceType": "cpe23Type",
     "referenceLocator": "cpe:2.3:a:g07cha:defender:v0.0.0-20180505193036-5665c627c814:*:*:*:*:*:*:*",
     "comment": ""
    },
    {
     "referenceCategory": "PACKAGE-MANAGER",
     "referenceType": "purl",
     "referenceLocator": "pkg:golang/github.com/g07cha/defender@v0.0.0-20180505193036-5665c627c814",
     "comment": ""
    }
   ]
  },
  {
   "name": "github.com/go-asn1-ber/asn1-ber",
   "SPDXID": "SPDXRef-Package-go-module-github.com-go-asn1-ber-asn1-ber-173edd1e7ad832de",
   "versionInfo": "v1.3.1",
   "downloadLocation": "NOASSERTION",
   "checksums": [
    {
     "algorithm": "SHA256",
     "checksumValue": "82f3ddbff1ebfbe4d114297451b3c51c2e783fd37d8e0b113e79a7af8d7d51c9"
    }
   ],
   "sourceInfo": "acquired package info from go module information: /portainer",
   "licenseConcluded": "NONE",
   "licenseDeclared": "NONE",
   "copyrightText": "NOASSERTION",
   "externalRefs": [
    {
     "referenceCategory": "SECURITY",
     "referenceType": "cpe23Type",
     "referenceLocator": "cpe:2.3:a:go-asn1-ber:asn1-ber:v1.3.1:*:*:*:*:*:*:*",
     "comment": ""
    },
    {
     "referenceCategory": "SECURITY",
     "referenceType": "cpe23Type",
     "referenceLocator": "cpe:2.3:a:go-asn1-ber:asn1_ber:v1.3.1:*:*:*:*:*:*:*",
     "comment": ""
    },
    {
     "referenceCategory": "SECURITY",
     "referenceType": "cpe23Type",
     "referenceLocator": "cpe:2.3:a:go_asn1_ber:asn1-ber:v1.3.1:*:*:*:*:*:*:*",
     "comment": ""
    },
    {
     "referenceCategory": "SECURITY",
     "referenceType": "cpe23Type",
     "referenceLocator": "cpe:2.3:a:go_asn1_ber:asn1_ber:v1.3.1:*:*:*:*:*:*:*",
     "comment": ""
    },
    {
     "referenceCategory": "SECURITY",
     "referenceType": "cpe23Type",
     "referenceLocator": "cpe:2.3:a:go-asn1:asn1-ber:v1.3.1:*:*:*:*:*:*:*",
     "comment": ""
    },
    {
     "referenceCategory": "SECURITY",
     "referenceType": "cpe23Type",
     "referenceLocator": "cpe:2.3:a:go-asn1:asn1_ber:v1.3.1:*:*:*:*:*:*:*",
     "comment": ""
    },
    {
     "referenceCategory": "SECURITY",
     "referenceType": "cpe23Type",
     "referenceLocator": "cpe:2.3:a:go_asn1:asn1-ber:v1.3.1:*:*:*:*:*:*:*",
     "comment": ""
    },
    {
     "referenceCategory": "SECURITY",
     "referenceType": "cpe23Type",
     "referenceLocator": "cpe:2.3:a:go_asn1:asn1_ber:v1.3.1:*:*:*:*:*:*:*",
     "comment": ""
    },
    {
     "referenceCategory": "SECURITY",
     "referenceType": "cpe23Type",
     "referenceLocator": "cpe:2.3:a:go:asn1-ber:v1.3.1:*:*:*:*:*:*:*",
     "comment": ""
    },
    {
     "referenceCategory": "SECURITY",
     "referenceType": "cpe23Type",
     "referenceLocator": "cpe:2.3:a:go:asn1_ber:v1.3.1:*:*:*:*:*:*:*",
     "comment": ""
    },
    {
     "referenceCategory": "PACKAGE-MANAGER",
     "referenceType": "purl",
     "referenceLocator": "pkg:golang/github.com/go-asn1-ber/asn1-ber@v1.3.1",
     "comment": ""
    }
   ]
  },
  {
   "name": "github.com/gofrs/uuid",
   "SPDXID": "SPDXRef-Package-go-module-github.com-gofrs-uuid-ae96e6038222d391",
   "versionInfo": "v3.2.0+incompatible",
   "downloadLocation": "NOASSERTION",
   "checksums": [
    {
     "algorithm": "SHA256",
     "checksumValue": "cb5da3464905c6c77b1a9a9d499fbf282b3f7c96eaa445d219de3e8df11a7b01"
    }
   ],
   "sourceInfo": "acquired package info from go module information: /portainer",
   "licenseConcluded": "NONE",
   "licenseDeclared": "NONE",
   "copyrightText": "NOASSERTION",
   "externalRefs": [
    {
     "referenceCategory": "SECURITY",
     "referenceType": "cpe23Type",
     "referenceLocator": "cpe:2.3:a:gofrs:uuid:v3.2.0\\+incompatible:*:*:*:*:*:*:*",
     "comment": ""
    },
    {
     "referenceCategory": "PACKAGE-MANAGER",
     "referenceType": "purl",
     "referenceLocator": "pkg:golang/github.com/gofrs/uuid@v3.2.0+incompatible",
     "comment": ""
    }
   ]
  },
  {
   "name": "github.com/gogo/protobuf",
   "SPDXID": "SPDXRef-Package-go-module-github.com-gogo-protobuf-d8416217401b216a",
   "versionInfo": "v1.2.2-0.20190723190241-65acae22fc9d",
   "downloadLocation": "NOASSERTION",
   "checksums": [
    {
     "algorithm": "SHA256",
     "checksumValue": "dcf688f29dec78dd3d5636d3602fd05a5519759d6a4b5cc68f2ecb1f65add3b2"
    }
   ],
   "sourceInfo": "acquired package info from go module information: /portainer",
   "licenseConcluded": "NONE",
   "licenseDeclared": "NONE",
   "copyrightText": "NOASSERTION",
   "externalRefs": [
    {
     "referenceCategory": "SECURITY",
     "referenceType": "cpe23Type",
     "referenceLocator": "cpe:2.3:a:gogo:protobuf:v1.2.2-0.20190723190241-65acae22fc9d:*:*:*:*:*:*:*",
     "comment": ""
    },
    {
     "referenceCategory": "PACKAGE-MANAGER",
     "referenceType": "purl",
     "referenceLocator": "pkg:golang/github.com/gogo/protobuf@v1.2.2-0.20190723190241-65acae22fc9d",
     "comment": ""
    }
   ]
  },
  {
   "name": "github.com/golang/protobuf",
   "SPDXID": "SPDXRef-Package-go-module-github.com-golang-protobuf-beb66ef1af5d367b",
   "versionInfo": "v1.3.2",
   "downloadLocation": "NOASSERTION",
   "checksums": [
    {
     "algorithm": "SHA256",
     "checksumValue": "ea7b0f63386ae6445e87a408988de4e6a5b33b83c46ef6c85b673049f47feb1b"
    }
   ],
   "sourceInfo": "acquired package info from go module information: /portainer",
   "licenseConcluded": "NONE",
   "licenseDeclared": "NONE",
   "copyrightText": "NOASSERTION",
   "externalRefs": [
    {
     "referenceCategory": "SECURITY",
     "referenceType": "cpe23Type",
     "referenceLocator": "cpe:2.3:a:golang:protobuf:v1.3.2:*:*:*:*:*:*:*",
     "comment": ""
    },
    {
     "referenceCategory": "PACKAGE-MANAGER",
     "referenceType": "purl",
     "referenceLocator": "pkg:golang/github.com/golang/protobuf@v1.3.2",
     "comment": ""
    }
   ]
  },
  {
   "name": "github.com/google/gofuzz",
   "SPDXID": "SPDXRef-Package-go-module-github.com-google-gofuzz-7535fddae2007c",
   "versionInfo": "v1.0.0",
   "downloadLocation": "NOASSERTION",
   "checksums": [
    {
     "algorithm": "SHA256",
     "checksumValue": "03c3de5b9f69c44f48a0546a069dfb53e99235a428678e85d5fd1ff3add7497c"
    }
   ],
   "sourceInfo": "acquired package info from go module information: /portainer",
   "licenseConcluded": "NONE",
   "licenseDeclared": "NONE",
   "copyrightText": "NOASSERTION",
   "externalRefs": [
    {
     "referenceCategory": "SECURITY",
     "referenceType": "cpe23Type",
     "referenceLocator": "cpe:2.3:a:google:gofuzz:v1.0.0:*:*:*:*:*:*:*",
     "comment": ""
    },
    {
     "referenceCategory": "PACKAGE-MANAGER",
     "referenceType": "purl",
     "referenceLocator": "pkg:golang/github.com/google/gofuzz@v1.0.0",
     "comment": ""
    }
   ]
  },
  {
   "name": "github.com/googleapis/gnostic",
   "SPDXID": "SPDXRef-Package-go-module-github.com-googleapis-gnostic-6390926691906c22",
   "versionInfo": "v0.0.0-20170729233727-0c5108395e2d",
   "downloadLocation": "NOASSERTION",
   "checksums": [
    {
     "algorithm": "SHA256",
     "checksumValue": "ed719a2f57ba6d84b5c88a271a9f7beb5131a4f3d5d6e8b44800b9f58b9b7bd9"
    }
   ],
   "sourceInfo": "acquired package info from go module information: /portainer",
   "licenseConcluded": "NONE",
   "licenseDeclared": "NONE",
   "copyrightText": "NOASSERTION",
   "externalRefs": [
    {
     "referenceCategory": "SECURITY",
     "referenceType": "cpe23Type",
     "referenceLocator": "cpe:2.3:a:googleapis:gnostic:v0.0.0-20170729233727-0c5108395e2d:*:*:*:*:*:*:*",
     "comment": ""
    },
    {
     "referenceCategory": "PACKAGE-MANAGER",
     "referenceType": "purl",
     "referenceLocator": "pkg:golang/github.com/googleapis/gnostic@v0.0.0-20170729233727-0c5108395e2d",
     "comment": ""
    }
   ]
  },
  {
   "name": "github.com/gorilla/mux",
   "SPDXID": "SPDXRef-Package-go-module-github.com-gorilla-mux-c28bd302b50ed53c",
   "versionInfo": "v1.7.3",
   "downloadLocation": "NOASSERTION",
   "checksums": [
    {
     "algorithm": "SHA256",
     "checksumValue": "8273f92738d53ae8990f4edf28a4e80803a34b4c8ea63fea3c44d35c2092ea1c"
    }
   ],
   "sourceInfo": "acquired package info from go module information: /portainer",
   "licenseConcluded": "NONE",
   "licenseDeclared": "NONE",
   "copyrightText": "NOASSERTION",
   "externalRefs": [
    {
     "referenceCategory": "SECURITY",
     "referenceType": "cpe23Type",
     "referenceLocator": "cpe:2.3:a:gorilla:mux:v1.7.3:*:*:*:*:*:*:*",
     "comment": ""
    },
    {
     "referenceCategory": "PACKAGE-MANAGER",
     "referenceType": "purl",
     "referenceLocator": "pkg:golang/github.com/gorilla/mux@v1.7.3",
     "comment": ""
    }
   ]
  },
  {
   "name": "github.com/gorilla/securecookie",
   "SPDXID": "SPDXRef-Package-go-module-github.com-gorilla-securecookie-3048730847240977",
   "versionInfo": "v1.1.1",
   "downloadLocation": "NOASSERTION",
   "checksums": [
    {
     "algorithm": "SHA256",
     "checksumValue": "9a2c3b24f855f9bfe5007497cf8a9dfe737d8d1880155e45c2378ac824bc06f4"
    }
   ],
   "sourceInfo": "acquired package info from go module information: /portainer",
   "licenseConcluded": "NONE",
   "licenseDeclared": "NONE",
   "copyrightText": "NOASSERTION",
   "externalRefs": [
    {
     "referenceCategory": "SECURITY",
     "referenceType": "cpe23Type",
     "referenceLocator": "cpe:2.3:a:gorilla:securecookie:v1.1.1:*:*:*:*:*:*:*",
     "comment": ""
    },
    {
     "referenceCategory": "PACKAGE-MANAGER",
     "referenceType": "purl",
     "referenceLocator": "pkg:golang/github.com/gorilla/securecookie@v1.1.1",
     "comment": ""
    }
   ]
  },
  {
   "name": "github.com/gorilla/websocket",
   "SPDXID": "SPDXRef-Package-go-module-github.com-gorilla-websocket-a17508d11d636fcb",
   "versionInfo": "v1.4.1",
   "downloadLocation": "NOASSERTION",
   "checksums": [
    {
     "algorithm": "SHA256",
     "checksumValue": "abb01e0c1a67064f00a20703e0349a83f524c3f295f988732e3d9b3f91ef2823"
    }
   ],
   "sourceInfo": "acquired package info from go module information: /portainer",
   "licenseConcluded": "NONE",
   "licenseDeclared": "NONE",
   "copyrightText": "NOASSERTION",
   "externalRefs": [
    {
     "referenceCategory": "SECURITY",
     "referenceType": "cpe23Type",
     "referenceLocator": "cpe:2.3:a:gorilla:websocket:v1.4.1:*:*:*:*:*:*:*",
     "comment": ""
    },
    {
     "referenceCategory": "PACKAGE-MANAGER",
     "referenceType": "purl",
     "referenceLocator": "pkg:golang/github.com/gorilla/websocket@v1.4.1",
     "comment": ""
    }
   ]
  },
  {
   "name": "github.com/imdario/mergo",
   "SPDXID": "SPDXRef-Package-go-module-github.com-imdario-mergo-3f43aa92a7ab6c17",
   "versionInfo": "v0.3.8",
   "downloadLocation": "NOASSERTION",
   "checksums": [
    {
     "algorithm": "SHA256",
     "checksumValue": "08680e91225ea8c466b740fd5cb584c5d4f89b8175bdddc557754fb7ed15c644"
    }
   ],
   "sourceInfo": "acquired package info from go module information: /portainer",
   "licenseConcluded": "NONE",
   "licenseDeclared": "NONE",
   "copyrightText": "NOASSERTION",
   "externalRefs": [
    {
     "referenceCategory": "SECURITY",
     "referenceType": "cpe23Type",
     "referenceLocator": "cpe:2.3:a:imdario:mergo:v0.3.8:*:*:*:*:*:*:*",
     "comment": ""
    },
    {
     "referenceCategory": "PACKAGE-MANAGER",
     "referenceType": "purl",
     "referenceLocator": "pkg:golang/github.com/imdario/mergo@v0.3.8",
     "comment": ""
    }
   ]
  },
  {
   "name": "github.com/jbenet/go-context",
   "SPDXID": "SPDXRef-Package-go-module-github.com-jbenet-go-context-2ea498247ba49347",
   "versionInfo": "v0.0.0-20150711004518-d14ea06fba99",
   "downloadLocation": "NOASSERTION",
   "checksums": [
    {
     "algorithm": "SHA256",
     "checksumValue": "05048578f03545624e968707e85c72f0c9b00edfb25506142ca7cdd11a1337c0"
    }
   ],
   "sourceInfo": "acquired package info from go module information: /portainer",
   "licenseConcluded": "NONE",
   "licenseDeclared": "NONE",
   "copyrightText": "NOASSERTION",
   "externalRefs": [
    {
     "referenceCategory": "SECURITY",
     "referenceType": "cpe23Type",
     "referenceLocator": "cpe:2.3:a:jbenet:go-context:v0.0.0-20150711004518-d14ea06fba99:*:*:*:*:*:*:*",
     "comment": ""
    },
    {
     "referenceCategory": "SECURITY",
     "referenceType": "cpe23Type",
     "referenceLocator": "cpe:2.3:a:jbenet:go_context:v0.0.0-20150711004518-d14ea06fba99:*:*:*:*:*:*:*",
     "comment": ""
    },
    {
     "referenceCategory": "PACKAGE-MANAGER",
     "referenceType": "purl",
     "referenceLocator": "pkg:golang/github.com/jbenet/go-context@v0.0.0-20150711004518-d14ea06fba99",
     "comment": ""
    }
   ]
  },
  {
   "name": "github.com/jpillora/ansi",
   "SPDXID": "SPDXRef-Package-go-module-github.com-jpillora-ansi-83188b0d652dec24",
   "versionInfo": "v0.0.0-20170202005112-f496b27cd669",
   "downloadLocation": "NOASSERTION",
   "checksums": [
    {
     "algorithm": "SHA256",
     "checksumValue": "979ac7fc29d556ef873f18edc6333dd271eb9b89e8bf78f7445f7feb652380bb"
    }
   ],
   "sourceInfo": "acquired package info from go module information: /portainer",
   "licenseConcluded": "NONE",
   "licenseDeclared": "NONE",
   "copyrightText": "NOASSERTION",
   "externalRefs": [
    {
     "referenceCategory": "SECURITY",
     "referenceType": "cpe23Type",
     "referenceLocator": "cpe:2.3:a:jpillora:ansi:v0.0.0-20170202005112-f496b27cd669:*:*:*:*:*:*:*",
     "comment": ""
    },
    {
     "referenceCategory": "PACKAGE-MANAGER",
     "referenceType": "purl",
     "referenceLocator": "pkg:golang/github.com/jpillora/ansi@v0.0.0-20170202005112-f496b27cd669",
     "comment": ""
    }
   ]
  },
  {
   "name": "github.com/jpillora/chisel",
   "SPDXID": "SPDXRef-Package-go-module-github.com-jpillora-chisel-67d590d70f50f0be",
   "versionInfo": "v0.0.0-20190724232113-f3a8df20e389",
   "downloadLocation": "NOASSERTION",
   "checksums": [
    {
     "algorithm": "SHA256",
     "checksumValue": "2b726ca11a97e82e20993bd8e23aad14609f2bcb93a23f4331a85c8896a85b01"
    }
   ],
   "sourceInfo": "acquired package info from go module information: /portainer",
   "licenseConcluded": "NONE",
   "licenseDeclared": "NONE",
   "copyrightText": "NOASSERTION",
   "externalRefs": [
    {
     "referenceCategory": "SECURITY",
     "referenceType": "cpe23Type",
     "referenceLocator": "cpe:2.3:a:jpillora:chisel:v0.0.0-20190724232113-f3a8df20e389:*:*:*:*:*:*:*",
     "comment": ""
    },
    {
     "referenceCategory": "PACKAGE-MANAGER",
     "referenceType": "purl",
     "referenceLocator": "pkg:golang/github.com/jpillora/chisel@v0.0.0-20190724232113-f3a8df20e389",
     "comment": ""
    }
   ]
  },
  {
   "name": "github.com/jpillora/requestlog",
   "SPDXID": "SPDXRef-Package-go-module-github.com-jpillora-requestlog-889394cca292e097",
   "versionInfo": "v0.0.0-20181015073026-df8817be5f82",
   "downloadLocation": "NOASSERTION",
   "checksums": [
    {
     "algorithm": "SHA256",
     "checksumValue": "eee7ddc82dda33115c0aff80059cbf76621518a16818d042a8e80b60f21c903f"
    }
   ],
   "sourceInfo": "acquired package info from go module information: /portainer",
   "licenseConcluded": "NONE",
   "licenseDeclared": "NONE",
   "copyrightText": "NOASSERTION",
   "externalRefs": [
    {
     "referenceCategory": "SECURITY",
     "referenceType": "cpe23Type",
     "referenceLocator": "cpe:2.3:a:jpillora:requestlog:v0.0.0-20181015073026-df8817be5f82:*:*:*:*:*:*:*",
     "comment": ""
    },
    {
     "referenceCategory": "PACKAGE-MANAGER",
     "referenceType": "purl",
     "referenceLocator": "pkg:golang/github.com/jpillora/requestlog@v0.0.0-20181015073026-df8817be5f82",
     "comment": ""
    }
   ]
  },
  {
   "name": "github.com/jpillora/sizestr",
   "SPDXID": "SPDXRef-Package-go-module-github.com-jpillora-sizestr-8108ab430fdc9459",
   "versionInfo": "v0.0.0-20160130011556-e2ea2fa42fb9",
   "downloadLocation": "NOASSERTION",
   "checksums": [
    {
     "algorithm": "SHA256",
     "checksumValue": "d1cf6372006d1d1b4353ffe34eb7028161ba5078cc672b62abfdd686b68d8143"
    }
   ],
   "sourceInfo": "acquired package info from go module information: /portainer",
   "licenseConcluded": "NONE",
   "licenseDeclared": "NONE",
   "copyrightText": "NOASSERTION",
   "externalRefs": [
    {
     "referenceCategory": "SECURITY",
     "referenceType": "cpe23Type",
     "referenceLocator": "cpe:2.3:a:jpillora:sizestr:v0.0.0-20160130011556-e2ea2fa42fb9:*:*:*:*:*:*:*",
     "comment": ""
    },
    {
     "referenceCategory": "PACKAGE-MANAGER",
     "referenceType": "purl",
     "referenceLocator": "pkg:golang/github.com/jpillora/sizestr@v0.0.0-20160130011556-e2ea2fa42fb9",
     "comment": ""
    }
   ]
  },
  {
   "name": "github.com/json-iterator/go",
   "SPDXID": "SPDXRef-Package-go-module-github.com-json-iterator-go-cb0a2d8d8413a182",
   "versionInfo": "v1.1.8",
   "downloadLocation": "NOASSERTION",
   "checksums": [
    {
     "algorithm": "SHA256",
     "checksumValue": "4225a414b2aad13ee6a73c0e4eee81ccd0db7d313c38bad885529830b178e8e9"
    }
   ],
   "sourceInfo": "acquired package info from go module information: /portainer",
   "licenseConcluded": "NONE",
   "licenseDeclared": "NONE",
   "copyrightText": "NOASSERTION",
   "externalRefs": [
    {
     "referenceCategory": "SECURITY",
     "referenceType": "cpe23Type",
     "referenceLocator": "cpe:2.3:a:json-iterator:go:v1.1.8:*:*:*:*:*:*:*",
     "comment": ""
    },
    {
     "referenceCategory": "SECURITY",
     "referenceType": "cpe23Type",
     "referenceLocator": "cpe:2.3:a:json_iterator:go:v1.1.8:*:*:*:*:*:*:*",
     "comment": ""
    },
    {
     "referenceCategory": "SECURITY",
     "referenceType": "cpe23Type",
     "referenceLocator": "cpe:2.3:a:json:go:v1.1.8:*:*:*:*:*:*:*",
     "comment": ""
    },
    {
     "referenceCategory": "PACKAGE-MANAGER",
     "referenceType": "purl",
     "referenceLocator": "pkg:golang/github.com/json-iterator/go@v1.1.8",
     "comment": ""
    }
   ]
  },
  {
   "name": "github.com/kevinburke/ssh_config",
   "SPDXID": "SPDXRef-Package-go-module-github.com-kevinburke-ssh-config-54f82f15b965c920",
   "versionInfo": "v0.0.0-20190725054713-01f96b0aa0cd",
   "downloadLocation": "NOASSERTION",
   "checksums": [
    {
     "algorithm": "SHA256",
     "checksumValue": "0a87a4c1d874bf6c2d1a9f469b3d597b779544058930ba24bcddd08ddcc21cb6"
    }
   ],
   "sourceInfo": "acquired package info from go module information: /portainer",
   "licenseConcluded": "NONE",
   "licenseDeclared": "NONE",
   "copyrightText": "NOASSERTION",
   "externalRefs": [
    {
     "referenceCategory": "SECURITY",
     "referenceType": "cpe23Type",
     "referenceLocator": "cpe:2.3:a:kevinburke:ssh-config:v0.0.0-20190725054713-01f96b0aa0cd:*:*:*:*:*:*:*",
     "comment": ""
    },
    {
     "referenceCategory": "SECURITY",
     "referenceType": "cpe23Type",
     "referenceLocator": "cpe:2.3:a:kevinburke:ssh_config:v0.0.0-20190725054713-01f96b0aa0cd:*:*:*:*:*:*:*",
     "comment": ""
    },
    {
     "referenceCategory": "PACKAGE-MANAGER",
     "referenceType": "purl",
     "referenceLocator": "pkg:golang/github.com/kevinburke/ssh_config@v0.0.0-20190725054713-01f96b0aa0cd",
     "comment": ""
    }
   ]
  },
  {
   "name": "github.com/koding/websocketproxy",
   "SPDXID": "SPDXRef-Package-go-module-github.com-koding-websocketproxy-736df86bc90ffba9",
   "versionInfo": "v0.0.0-20181220232114-7ed82d81a28c",
   "downloadLocation": "NOASSERTION",
   "checksums": [
    {
     "algorithm": "SHA256",
     "checksumValue": "37b0382420361be8f97ee1710ac26a8c553fb197b49a3f07d2c4a84b06da8a4c"
    }
   ],
   "sourceInfo": "acquired package info from go module information: /portainer",
   "licenseConcluded": "NONE",
   "licenseDeclared": "NONE",
   "copyrightText": "NOASSERTION",
   "externalRefs": [
    {
     "referenceCategory": "SECURITY",
     "referenceType": "cpe23Type",
     "referenceLocator": "cpe:2.3:a:koding:websocketproxy:v0.0.0-20181220232114-7ed82d81a28c:*:*:*:*:*:*:*",
     "comment": ""
    },
    {
     "referenceCategory": "PACKAGE-MANAGER",
     "referenceType": "purl",
     "referenceLocator": "pkg:golang/github.com/koding/websocketproxy@v0.0.0-20181220232114-7ed82d81a28c",
     "comment": ""
    }
   ]
  },
  {
   "name": "github.com/mattn/go-shellwords",
   "SPDXID": "SPDXRef-Package-go-module-github.com-mattn-go-shellwords-747b7bbf17804d53",
   "versionInfo": "v1.0.6",
   "downloadLocation": "NOASSERTION",
   "checksums": [
    {
     "algorithm": "SHA256",
     "checksumValue": "f49a24e6920b8b94b53270e2ac6553b9f606b64b14b3f57605650fdd991e5142"
    }
   ],
   "sourceInfo": "acquired package info from go module information: /portainer",
   "licenseConcluded": "NONE",
   "licenseDeclared": "NONE",
   "copyrightText": "NOASSERTION",
   "externalRefs": [
    {
     "referenceCategory": "SECURITY",
     "referenceType": "cpe23Type",
     "referenceLocator": "cpe:2.3:a:mattn:go-shellwords:v1.0.6:*:*:*:*:*:*:*",
     "comment": ""
    },
    {
     "referenceCategory": "SECURITY",
     "referenceType": "cpe23Type",
     "referenceLocator": "cpe:2.3:a:mattn:go_shellwords:v1.0.6:*:*:*:*:*:*:*",
     "comment": ""
    },
    {
     "referenceCategory": "PACKAGE-MANAGER",
     "referenceType": "purl",
     "referenceLocator": "pkg:golang/github.com/mattn/go-shellwords@v1.0.6",
     "comment": ""
    }
   ]
  },
  {
   "name": "github.com/matttproud/golang_protobuf_extensions",
   "SPDXID": "SPDXRef-Package-go-module-github.com-matttproud-golang-protobuf-extensions-8d07d9a31450552",
   "versionInfo": "v1.0.1",
   "downloadLocation": "NOASSERTION",
   "checksums": [
    {
     "algorithm": "SHA256",
     "checksumValue": "e21a7d8e41f184c1e4aa4ac1dc8c748de812e6cc7f464a80465b1667aa48c225"
    }
   ],
   "sourceInfo": "acquired package info from go module information: /portainer",
   "licenseConcluded": "NONE",
   "licenseDeclared": "NONE",
   "copyrightText": "NOASSERTION",
   "externalRefs": [
    {
     "referenceCategory": "SECURITY",
     "referenceType": "cpe23Type",
     "referenceLocator": "cpe:2.3:a:matttproud:golang-protobuf-extensions:v1.0.1:*:*:*:*:*:*:*",
     "comment": ""
    },
    {
     "referenceCategory": "SECURITY",
     "referenceType": "cpe23Type",
     "referenceLocator": "cpe:2.3:a:matttproud:golang_protobuf_extensions:v1.0.1:*:*:*:*:*:*:*",
     "comment": ""
    },
    {
     "referenceCategory": "PACKAGE-MANAGER",
     "referenceType": "purl",
     "referenceLocator": "pkg:golang/github.com/matttproud/golang_protobuf_extensions@v1.0.1",
     "comment": ""
    }
   ]
  },
  {
   "name": "github.com/mitchellh/go-homedir",
   "SPDXID": "SPDXRef-Package-go-module-github.com-mitchellh-go-homedir-b92150f80d684f88",
   "versionInfo": "v1.1.0",
   "downloadLocation": "NOASSERTION",
   "checksums": [
    {
     "algorithm": "SHA256",
     "checksumValue": "96e905f738971710c53e4035becaf9ce97355ee3c39ffc059edab9986fb81346"
    }
   ],
   "sourceInfo": "acquired package info from go module information: /portainer",
   "licenseConcluded": "NONE",
   "licenseDeclared": "NONE",
   "copyrightText": "NOASSERTION",
   "externalRefs": [
    {
     "referenceCategory": "SECURITY",
     "referenceType": "cpe23Type",
     "referenceLocator": "cpe:2.3:a:mitchellh:go-homedir:v1.1.0:*:*:*:*:*:*:*",
     "comment": ""
    },
    {
     "referenceCategory": "SECURITY",
     "referenceType": "cpe23Type",
     "referenceLocator": "cpe:2.3:a:mitchellh:go_homedir:v1.1.0:*:*:*:*:*:*:*",
     "comment": ""
    },
    {
     "referenceCategory": "PACKAGE-MANAGER",
     "referenceType": "purl",
     "referenceLocator": "pkg:golang/github.com/mitchellh/go-homedir@v1.1.0",
     "comment": ""
    }
   ]
  },
  {
   "name": "github.com/mitchellh/mapstructure",
   "SPDXID": "SPDXRef-Package-go-module-github.com-mitchellh-mapstructure-5c29ca266332cf6e",
   "versionInfo": "v1.1.2",
   "downloadLocation": "NOASSERTION",
   "checksums": [
    {
     "algorithm": "SHA256",
     "checksumValue": "7e6358570aa749f07d99953a392d8ee86b1733ec1cb24643b8a433bcdd440de1"
    }
   ],
   "sourceInfo": "acquired package info from go module information: /portainer",
   "licenseConcluded": "NONE",
   "licenseDeclared": "NONE",
   "copyrightText": "NOASSERTION",
   "externalRefs": [
    {
     "referenceCategory": "SECURITY",
     "referenceType": "cpe23Type",
     "referenceLocator": "cpe:2.3:a:mitchellh:mapstructure:v1.1.2:*:*:*:*:*:*:*",
     "comment": ""
    },
    {
     "referenceCategory": "PACKAGE-MANAGER",
     "referenceType": "purl",
     "referenceLocator": "pkg:golang/github.com/mitchellh/mapstructure@v1.1.2",
     "comment": ""
    }
   ]
  },
  {
   "name": "github.com/modern-go/concurrent",
   "SPDXID": "SPDXRef-Package-go-module-github.com-modern-go-concurrent-52f87f0f9bd204c5",
   "versionInfo": "v0.0.0-20180306012644-bacd9c7ef1dd",
   "downloadLocation": "NOASSERTION",
   "checksums": [
    {
     "algorithm": "SHA256",
     "checksumValue": "4d12da67d703ff0f0f561f779ec3d76b556b43a8e5c0be6837c975e1095c35f8"
    }
   ],
   "sourceInfo": "acquired package info from go module information: /portainer",
   "licenseConcluded": "NONE",
   "licenseDeclared": "NONE",
   "copyrightText": "NOASSERTION",
   "externalRefs": [
    {
     "referenceCategory": "SECURITY",
     "referenceType": "cpe23Type",
     "referenceLocator": "cpe:2.3:a:modern-go:concurrent:v0.0.0-20180306012644-bacd9c7ef1dd:*:*:*:*:*:*:*",
     "comment": ""
    },
    {
     "referenceCategory": "SECURITY",
     "referenceType": "cpe23Type",
     "referenceLocator": "cpe:2.3:a:modern_go:concurrent:v0.0.0-20180306012644-bacd9c7ef1dd:*:*:*:*:*:*:*",
     "comment": ""
    },
    {
     "referenceCategory": "SECURITY",
     "referenceType": "cpe23Type",
     "referenceLocator": "cpe:2.3:a:modern:concurrent:v0.0.0-20180306012644-bacd9c7ef1dd:*:*:*:*:*:*:*",
     "comment": ""
    },
    {
     "referenceCategory": "PACKAGE-MANAGER",
     "referenceType": "purl",
     "referenceLocator": "pkg:golang/github.com/modern-go/concurrent@v0.0.0-20180306012644-bacd9c7ef1dd",
     "comment": ""
    }
   ]
  },
  {
   "name": "github.com/modern-go/reflect2",
   "SPDXID": "SPDXRef-Package-go-module-github.com-modern-go-reflect2-2afca780615ecf5",
   "versionInfo": "v1.0.1",
   "downloadLocation": "NOASSERTION",
   "checksums": [
    {
     "algorithm": "SHA256",
     "checksumValue": "f5fe35dacfba4666172d665213355580f18aec2d8fa611e3e5126bbdfc7d0162"
    }
   ],
   "sourceInfo": "acquired package info from go module information: /portainer",
   "licenseConcluded": "NONE",
   "licenseDeclared": "NONE",
   "copyrightText": "NOASSERTION",
   "externalRefs": [
    {
     "referenceCategory": "SECURITY",
     "referenceType": "cpe23Type",
     "referenceLocator": "cpe:2.3:a:modern-go:reflect2:v1.0.1:*:*:*:*:*:*:*",
     "comment": ""
    },
    {
     "referenceCategory": "SECURITY",
     "referenceType": "cpe23Type",
     "referenceLocator": "cpe:2.3:a:modern_go:reflect2:v1.0.1:*:*:*:*:*:*:*",
     "comment": ""
    },
    {
     "referenceCategory": "SECURITY",
     "referenceType": "cpe23Type",
     "referenceLocator": "cpe:2.3:a:modern:reflect2:v1.0.1:*:*:*:*:*:*:*",
     "comment": ""
    },
    {
     "referenceCategory": "PACKAGE-MANAGER",
     "referenceType": "purl",
     "referenceLocator": "pkg:golang/github.com/modern-go/reflect2@v1.0.1",
     "comment": ""
    }
   ]
  },
  {
   "name": "github.com/morikuni/aec",
   "SPDXID": "SPDXRef-Package-go-module-github.com-morikuni-aec-9fc8cc9cd5de11fe",
   "versionInfo": "v0.0.0-20170113033406-39771216ff4c",
   "downloadLocation": "NOASSERTION",
   "checksums": [
    {
     "algorithm": "SHA256",
     "checksumValue": "9d7c65e4faef566d8bff00b2f1d42ee83313c07e2822e18df06243025a837551"
    }
   ],
   "sourceInfo": "acquired package info from go module information: /portainer",
   "licenseConcluded": "NONE",
   "licenseDeclared": "NONE",
   "copyrightText": "NOASSERTION",
   "externalRefs": [
    {
     "referenceCategory": "SECURITY",
     "referenceType": "cpe23Type",
     "referenceLocator": "cpe:2.3:a:morikuni:aec:v0.0.0-20170113033406-39771216ff4c:*:*:*:*:*:*:*",
     "comment": ""
    },
    {
     "referenceCategory": "PACKAGE-MANAGER",
     "referenceType": "purl",
     "referenceLocator": "pkg:golang/github.com/morikuni/aec@v0.0.0-20170113033406-39771216ff4c",
     "comment": ""
    }
   ]
  },
  {
   "name": "github.com/opencontainers/go-digest",
   "SPDXID": "SPDXRef-Package-go-module-github.com-opencontainers-go-digest-b219916e6e030cb0",
   "versionInfo": "v0.0.0-20170106003457-a6d0ee40d420",
   "downloadLocation": "NOASSERTION",
   "checksums": [
    {
     "algorithm": "SHA256",
     "checksumValue": "62edfaf35ca46070df2e823a5d58cbe095a6904fb74d7f727c85b04428759053"
    }
   ],
   "sourceInfo": "acquired package info from go module information: /portainer",
   "licenseConcluded": "NONE",
   "licenseDeclared": "NONE",
   "copyrightText": "NOASSERTION",
   "externalRefs": [
    {
     "referenceCategory": "SECURITY",
     "referenceType": "cpe23Type",
     "referenceLocator": "cpe:2.3:a:opencontainers:go-digest:v0.0.0-20170106003457-a6d0ee40d420:*:*:*:*:*:*:*",
     "comment": ""
    },
    {
     "referenceCategory": "SECURITY",
     "referenceType": "cpe23Type",
     "referenceLocator": "cpe:2.3:a:opencontainers:go_digest:v0.0.0-20170106003457-a6d0ee40d420:*:*:*:*:*:*:*",
     "comment": ""
    },
    {
     "referenceCategory": "PACKAGE-MANAGER",
     "referenceType": "purl",
     "referenceLocator": "pkg:golang/github.com/opencontainers/go-digest@v0.0.0-20170106003457-a6d0ee40d420",
     "comment": ""
    }
   ]
  },
  {
   "name": "github.com/opencontainers/image-spec",
   "SPDXID": "SPDXRef-Package-go-module-github.com-opencontainers-image-spec-c33dc642620d9eb7",
   "versionInfo": "v0.0.0-20170515205857-f03dbe35d449",
   "downloadLocation": "NOASSERTION",
   "checksums": [
    {
     "algorithm": "SHA256",
     "checksumValue": "02af221bbd9a90f6ff92ccc4ee4b19e65755f8960f6228bf2993b1969245d3bb"
    }
   ],
   "sourceInfo": "acquired package info from go module information: /portainer",
   "licenseConcluded": "NONE",
   "licenseDeclared": "NONE",
   "copyrightText": "NOASSERTION",
   "externalRefs": [
    {
     "referenceCategory": "SECURITY",
     "referenceType": "cpe23Type",
     "referenceLocator": "cpe:2.3:a:opencontainers:image-spec:v0.0.0-20170515205857-f03dbe35d449:*:*:*:*:*:*:*",
     "comment": ""
    },
    {
     "referenceCategory": "SECURITY",
     "referenceType": "cpe23Type",
     "referenceLocator": "cpe:2.3:a:opencontainers:image_spec:v0.0.0-20170515205857-f03dbe35d449:*:*:*:*:*:*:*",
     "comment": ""
    },
    {
     "referenceCategory": "PACKAGE-MANAGER",
     "referenceType": "purl",
     "referenceLocator": "pkg:golang/github.com/opencontainers/image-spec@v0.0.0-20170515205857-f03dbe35d449",
     "comment": ""
    }
   ]
  },
  {
   "name": "github.com/opencontainers/runc",
   "SPDXID": "SPDXRef-Package-go-module-github.com-opencontainers-runc-37df5c180be744fd",
   "versionInfo": "v0.0.0-20161109192122-51371867a01c",
   "downloadLocation": "NOASSERTION",
   "checksums": [
    {
     "algorithm": "SHA256",
     "checksumValue": "88e31b6bf2a66978125f93c52aed6eeacf836578aaf84ccf6b26b06bbeb0e9a0"
    }
   ],
   "sourceInfo": "acquired package info from go module information: /portainer",
   "licenseConcluded": "NONE",
   "licenseDeclared": "NONE",
   "copyrightText": "NOASSERTION",
   "externalRefs": [
    {
     "referenceCategory": "SECURITY",
     "referenceType": "cpe23Type",
     "referenceLocator": "cpe:2.3:a:opencontainers:runc:v0.0.0-20161109192122-51371867a01c:*:*:*:*:*:*:*",
     "comment": ""
    },
    {
     "referenceCategory": "PACKAGE-MANAGER",
     "referenceType": "purl",
     "referenceLocator": "pkg:golang/github.com/opencontainers/runc@v0.0.0-20161109192122-51371867a01c",
     "comment": ""
    }
   ]
  },
  {
   "name": "github.com/orcaman/concurrent-map",
   "SPDXID": "SPDXRef-Package-go-module-github.com-orcaman-concurrent-map-4c60de22d230134a",
   "versionInfo": "v0.0.0-20190826125027-8c72a8bb44f6",
   "downloadLocation": "NOASSERTION",
   "checksums": [
    {
     "algorithm": "SHA256",
     "checksumValue": "94d096e931eb08a062241a73f246d51a30bb32074218ac2ebc181cecba03eacc"
    }
   ],
   "sourceInfo": "acquired package info from go module information: /portainer",
   "licenseConcluded": "NONE",
   "licenseDeclared": "NONE",
   "copyrightText": "NOASSERTION",
   "externalRefs": [
    {
     "referenceCategory": "SECURITY",
     "referenceType": "cpe23Type",
     "referenceLocator": "cpe:2.3:a:orcaman:concurrent-map:v0.0.0-20190826125027-8c72a8bb44f6:*:*:*:*:*:*:*",
     "comment": ""
    },
    {
     "referenceCategory": "SECURITY",
     "referenceType": "cpe23Type",
     "referenceLocator": "cpe:2.3:a:orcaman:concurrent_map:v0.0.0-20190826125027-8c72a8bb44f6:*:*:*:*:*:*:*",
     "comment": ""
    },
    {
     "referenceCategory": "PACKAGE-MANAGER",
     "referenceType": "purl",
     "referenceLocator": "pkg:golang/github.com/orcaman/concurrent-map@v0.0.0-20190826125027-8c72a8bb44f6",
     "comment": ""
    }
   ]
  },
  {
   "name": "github.com/pkg/errors",
   "SPDXID": "SPDXRef-Package-go-module-github.com-pkg-errors-8914b2c95f7763b2",
   "versionInfo": "v0.8.1",
   "downloadLocation": "NOASSERTION",
   "checksums": [
    {
     "algorithm": "SHA256",
     "checksumValue": "894454ad11b13d434f772e7f1d14a6f988faa2427a52d2c834dd10f4ce3e8772"
    }
   ],
   "sourceInfo": "acquired package info from go module information: /portainer",
   "licenseConcluded": "NONE",
   "licenseDeclared": "NONE",
   "copyrightText": "NOASSERTION",
   "externalRefs": [
    {
     "referenceCategory": "SECURITY",
     "referenceType": "cpe23Type",
     "referenceLocator": "cpe:2.3:a:pkg:errors:v0.8.1:*:*:*:*:*:*:*",
     "comment": ""
    },
    {
     "referenceCategory": "PACKAGE-MANAGER",
     "referenceType": "purl",
     "referenceLocator": "pkg:golang/github.com/pkg/errors@v0.8.1",
     "comment": ""
    }
   ]
  },
  {
   "name": "github.com/portainer/libcompose",
   "SPDXID": "SPDXRef-Package-go-module-github.com-portainer-libcompose-6531f0033be44850",
   "versionInfo": "v0.5.1-0.20191128210235-7e42ca632b24",
   "downloadLocation": "NOASSERTION",
   "checksums": [
    {
     "algorithm": "SHA256",
     "checksumValue": "83173aece87c0dd232276625c0bc1eacaa854ff4af72404a88416a514e86d00c"
    }
   ],
   "sourceInfo": "acquired package info from go module information: /portainer",
   "licenseConcluded": "NONE",
   "licenseDeclared": "NONE",
   "copyrightText": "NOASSERTION",
   "externalRefs": [
    {
     "referenceCategory": "SECURITY",
     "referenceType": "cpe23Type",
     "referenceLocator": "cpe:2.3:a:portainer:libcompose:v0.5.1-0.20191128210235-7e42ca632b24:*:*:*:*:*:*:*",
     "comment": ""
    },
    {
     "referenceCategory": "PACKAGE-MANAGER",
     "referenceType": "purl",
     "referenceLocator": "pkg:golang/github.com/portainer/libcompose@v0.5.1-0.20191128210235-7e42ca632b24",
     "comment": ""
    }
   ]
  },
  {
   "name": "github.com/portainer/libcrypto",
   "SPDXID": "SPDXRef-Package-go-module-github.com-portainer-libcrypto-d1afd9064461364b",
   "versionInfo": "v0.0.0-20190723020515-23ebe86ab2c2",
   "downloadLocation": "NOASSERTION",
   "checksums": [
    {
     "algorithm": "SHA256",
     "checksumValue": "d0f7e018bcacf721ebe2bb678ab8345b40a3befebf0f3c41219939b15e7ddb4f"
    }
   ],
   "sourceInfo": "acquired package info from go module information: /portainer",
   "licenseConcluded": "NONE",
   "licenseDeclared": "NONE",
   "copyrightText": "NOASSERTION",
   "externalRefs": [
    {
     "referenceCategory": "SECURITY",
     "referenceType": "cpe23Type",
     "referenceLocator": "cpe:2.3:a:portainer:libcrypto:v0.0.0-20190723020515-23ebe86ab2c2:*:*:*:*:*:*:*",
     "comment": ""
    },
    {
     "referenceCategory": "PACKAGE-MANAGER",
     "referenceType": "purl",
     "referenceLocator": "pkg:golang/github.com/portainer/libcrypto@v0.0.0-20190723020515-23ebe86ab2c2",
     "comment": ""
    }
   ]
  },
  {
   "name": "github.com/portainer/libhttp",
   "SPDXID": "SPDXRef-Package-go-module-github.com-portainer-libhttp-7749b6d75779cf5",
   "versionInfo": "v0.0.0-20190806161843-ba068f58be33",
   "downloadLocation": "NOASSERTION",
   "checksums": [
    {
     "algorithm": "SHA256",
     "checksumValue": "1fc1d1d9d1dd05ff0700d4a4532570e28f3ee2d7a019c77ecf2299ddee7df482"
    }
   ],
   "sourceInfo": "acquired package info from go module information: /portainer",
   "licenseConcluded": "NONE",
   "licenseDeclared": "NONE",
   "copyrightText": "NOASSERTION",
   "externalRefs": [
    {
     "referenceCategory": "SECURITY",
     "referenceType": "cpe23Type",
     "referenceLocator": "cpe:2.3:a:portainer:libhttp:v0.0.0-20190806161843-ba068f58be33:*:*:*:*:*:*:*",
     "comment": ""
    },
    {
     "referenceCategory": "PACKAGE-MANAGER",
     "referenceType": "purl",
     "referenceLocator": "pkg:golang/github.com/portainer/libhttp@v0.0.0-20190806161843-ba068f58be33",
     "comment": ""
    }
   ]
  },
  {
   "name": "github.com/portainer/portainer/api",
   "SPDXID": "SPDXRef-Package-go-module-github.com-portainer-portainer-api-fc9f24a8c1e86857",
   "versionInfo": "(devel)",
   "downloadLocation": "NOASSERTION",
   "sourceInfo": "acquired package info from go module information: /portainer",
   "licenseConcluded": "NONE",
   "licenseDeclared": "NONE",
   "copyrightText": "NOASSERTION",
   "externalRefs": [
    {
     "referenceCategory": "SECURITY",
     "referenceType": "cpe23Type",
     "referenceLocator": "cpe:2.3:a:portainer:portainer\\/api:\\(devel\\):*:*:*:*:*:*:*",
     "comment": ""
    },
    {
     "referenceCategory": "PACKAGE-MANAGER",
     "referenceType": "purl",
     "referenceLocator": "pkg:golang/github.com/portainer/portainer/api@(devel)",
     "comment": ""
    }
   ]
  },
  {
   "name": "github.com/prometheus/client_golang",
   "SPDXID": "SPDXRef-Package-go-module-github.com-prometheus-client-golang-be27e561eebcda96",
   "versionInfo": "v1.1.0",
   "downloadLocation": "NOASSERTION",
   "checksums": [
    {
     "algorithm": "SHA256",
     "checksumValue": "050e771ed0667ce8ad1316b027a2e8900e31f28bffcf449861bd3e1f125f448f"
    }
   ],
   "sourceInfo": "acquired package info from go module information: /portainer",
   "licenseConcluded": "NONE",
   "licenseDeclared": "NONE",
   "copyrightText": "NOASSERTION",
   "externalRefs": [
    {
     "referenceCategory": "SECURITY",
     "referenceType": "cpe23Type",
     "referenceLocator": "cpe:2.3:a:prometheus:client-golang:v1.1.0:*:*:*:*:*:*:*",
     "comment": ""
    },
    {
     "referenceCategory": "SECURITY",
     "referenceType": "cpe23Type",
     "referenceLocator": "cpe:2.3:a:prometheus:client_golang:v1.1.0:*:*:*:*:*:*:*",
     "comment": ""
    },
    {
     "referenceCategory": "PACKAGE-MANAGER",
     "referenceType": "purl",
     "referenceLocator": "pkg:golang/github.com/prometheus/client_golang@v1.1.0",
     "comment": ""
    }
   ]
  },
  {
   "name": "github.com/prometheus/client_model",
   "SPDXID": "SPDXRef-Package-go-module-github.com-prometheus-client-model-bf8638582ccd369a",
   "versionInfo": "v0.0.0-20190129233127-fd36f4220a90",
   "downloadLocation": "NOASSERTION",
   "checksums": [
    {
     "algorithm": "SHA256",
     "checksumValue": "4bf616c16c7f440f2b4fcb4a151b8651986e03dd0ec880693c25e471bc14f031"
    }
   ],
   "sourceInfo": "acquired package info from go module information: /portainer",
   "licenseConcluded": "NONE",
   "licenseDeclared": "NONE",
   "copyrightText": "NOASSERTION",
   "externalRefs": [
    {
     "referenceCategory": "SECURITY",
     "referenceType": "cpe23Type",
     "referenceLocator": "cpe:2.3:a:prometheus:client-model:v0.0.0-20190129233127-fd36f4220a90:*:*:*:*:*:*:*",
     "comment": ""
    },
    {
     "referenceCategory": "SECURITY",
     "referenceType": "cpe23Type",
     "referenceLocator": "cpe:2.3:a:prometheus:client_model:v0.0.0-20190129233127-fd36f4220a90:*:*:*:*:*:*:*",
     "comment": ""
    },
    {
     "referenceCategory": "PACKAGE-MANAGER",
     "referenceType": "purl",
     "referenceLocator": "pkg:golang/github.com/prometheus/client_model@v0.0.0-20190129233127-fd36f4220a90",
     "comment": ""
    }
   ]
  },
  {
   "name": "github.com/prometheus/common",
   "SPDXID": "SPDXRef-Package-go-module-github.com-prometheus-common-bb7d21bfc5937640",
   "versionInfo": "v0.6.0",
   "downloadLocation": "NOASSERTION",
   "checksums": [
    {
     "algorithm": "SHA256",
     "checksumValue": "911862b98497477faebf621b55b6615312b9cd50ffda9a7719dd8fa6f3e4a44a"
    }
   ],
   "sourceInfo": "acquired package info from go module information: /portainer",
   "licenseConcluded": "NONE",
   "licenseDeclared": "NONE",
   "copyrightText": "NOASSERTION",
   "externalRefs": [
    {
     "referenceCategory": "SECURITY",
     "referenceType": "cpe23Type",
     "referenceLocator": "cpe:2.3:a:prometheus:common:v0.6.0:*:*:*:*:*:*:*",
     "comment": ""
    },
    {
     "referenceCategory": "PACKAGE-MANAGER",
     "referenceType": "purl",
     "referenceLocator": "pkg:golang/github.com/prometheus/common@v0.6.0",
     "comment": ""
    }
   ]
  },
  {
   "name": "github.com/prometheus/procfs",
   "SPDXID": "SPDXRef-Package-go-module-github.com-prometheus-procfs-10476316e8af3b36",
   "versionInfo": "v0.0.3",
   "downloadLocation": "NOASSERTION",
   "checksums": [
    {
     "algorithm": "SHA256",
     "checksumValue": "093c1f9f38d0fbc752e8c8471eee18b305400fdf6c2f6c233ea3fe56451198a1"
    }
   ],
   "sourceInfo": "acquired package info from go module information: /portainer",
   "licenseConcluded": "NONE",
   "licenseDeclared": "NONE",
   "copyrightText": "NOASSERTION",
   "externalRefs": [
    {
     "referenceCategory": "SECURITY",
     "referenceType": "cpe23Type",
     "referenceLocator": "cpe:2.3:a:prometheus:procfs:v0.0.3:*:*:*:*:*:*:*",
     "comment": ""
    },
    {
     "referenceCategory": "PACKAGE-MANAGER",
     "referenceType": "purl",
     "referenceLocator": "pkg:golang/github.com/prometheus/procfs@v0.0.3",
     "comment": ""
    }
   ]
  },
  {
   "name": "github.com/robfig/cron/v3",
   "SPDXID": "SPDXRef-Package-go-module-github.com-robfig-cron-v3-b5d0dce417bc431f",
   "versionInfo": "v3.0.0",
   "downloadLocation": "NOASSERTION",
   "checksums": [
    {
     "algorithm": "SHA256",
     "checksumValue": "910e826fb6873874d2ccd54d1219a9f0471628b6f809b88c5bd87d5722213b81"
    }
   ],
   "sourceInfo": "acquired package info from go module information: /portainer",
   "licenseConcluded": "NONE",
   "licenseDeclared": "NONE",
   "copyrightText": "NOASSERTION",
   "externalRefs": [
    {
     "referenceCategory": "SECURITY",
     "referenceType": "cpe23Type",
     "referenceLocator": "cpe:2.3:a:robfig:cron\\/v3:v3.0.0:*:*:*:*:*:*:*",
     "comment": ""
    },
    {
     "referenceCategory": "PACKAGE-MANAGER",
     "referenceType": "purl",
     "referenceLocator": "pkg:golang/github.com/robfig/cron/v3@v3.0.0",
     "comment": ""
    }
   ]
  },
  {
   "name": "github.com/sergi/go-diff",
   "SPDXID": "SPDXRef-Package-go-module-github.com-sergi-go-diff-cdd9c73ec84d89fc",
   "versionInfo": "v1.0.0",
   "downloadLocation": "NOASSERTION",
   "checksums": [
    {
     "algorithm": "SHA256",
     "checksumValue": "2a971adea44daddb8d9ce41e6b305dd32b1a2ab509888b88487c688244fd44f4"
    }
   ],
   "sourceInfo": "acquired package info from go module information: /portainer",
   "licenseConcluded": "NONE",
   "licenseDeclared": "NONE",
   "copyrightText": "NOASSERTION",
   "externalRefs": [
    {
     "referenceCategory": "SECURITY",
     "referenceType": "cpe23Type",
     "referenceLocator": "cpe:2.3:a:sergi:go-diff:v1.0.0:*:*:*:*:*:*:*",
     "comment": ""
    },
    {
     "referenceCategory": "SECURITY",
     "referenceType": "cpe23Type",
     "referenceLocator": "cpe:2.3:a:sergi:go_diff:v1.0.0:*:*:*:*:*:*:*",
     "comment": ""
    },
    {
     "referenceCategory": "PACKAGE-MANAGER",
     "referenceType": "purl",
     "referenceLocator": "pkg:golang/github.com/sergi/go-diff@v1.0.0",
     "comment": ""
    }
   ]
  },
  {
   "name": "github.com/sirupsen/logrus",
   "SPDXID": "SPDXRef-Package-go-module-github.com-sirupsen-logrus-42c03e8efa720325",
   "versionInfo": "v1.2.0",
   "downloadLocation": "NOASSERTION",
   "checksums": [
    {
     "algorithm": "SHA256",
     "checksumValue": "8ee4e0ba8624e6a236d69c324d763707763970e4c7dd9532642835bff9a286ea"
    }
   ],
   "sourceInfo": "acquired package info from go module information: /portainer",
   "licenseConcluded": "NONE",
   "licenseDeclared": "NONE",
   "copyrightText": "NOASSERTION",
   "externalRefs": [
    {
     "referenceCategory": "SECURITY",
     "referenceType": "cpe23Type",
     "referenceLocator": "cpe:2.3:a:sirupsen:logrus:v1.2.0:*:*:*:*:*:*:*",
     "comment": ""
    },
    {
     "referenceCategory": "PACKAGE-MANAGER",
     "referenceType": "purl",
     "referenceLocator": "pkg:golang/github.com/sirupsen/logrus@v1.2.0",
     "comment": ""
    }
   ]
  },
  {
   "name": "github.com/spf13/pflag",
   "SPDXID": "SPDXRef-Package-go-module-github.com-spf13-pflag-500544371b403fa4",
   "versionInfo": "v1.0.5",
   "downloadLocation": "NOASSERTION",
   "checksums": [
    {
     "algorithm": "SHA256",
     "checksumValue": "8b2f951543823f56bef3216da3f76b836089e6ed3246807b7d9c370cabff2570"
    }
   ],
   "sourceInfo": "acquired package info from go module information: /portainer",
   "licenseConcluded": "NONE",
   "licenseDeclared": "NONE",
   "copyrightText": "NOASSERTION",
   "externalRefs": [
    {
     "referenceCategory": "SECURITY",
     "referenceType": "cpe23Type",
     "referenceLocator": "cpe:2.3:a:spf13:pflag:v1.0.5:*:*:*:*:*:*:*",
     "comment": ""
    },
    {
     "referenceCategory": "PACKAGE-MANAGER",
     "referenceType": "purl",
     "referenceLocator": "pkg:golang/github.com/spf13/pflag@v1.0.5",
     "comment": ""
    }
   ]
  },
  {
   "name": "github.com/src-d/gcfg",
   "SPDXID": "SPDXRef-Package-go-module-github.com-src-d-gcfg-89a94a83b653f621",
   "versionInfo": "v1.4.0",
   "downloadLocation": "NOASSERTION",
   "checksums": [
    {
     "algorithm": "SHA256",
     "checksumValue": "c576cd4790252d2037d79c7650ef9f4d24805c20dff80af7f3fea8c866c3290e"
    }
   ],
   "sourceInfo": "acquired package info from go module information: /portainer",
   "licenseConcluded": "NONE",
   "licenseDeclared": "NONE",
   "copyrightText": "NOASSERTION",
   "externalRefs": [
    {
     "referenceCategory": "SECURITY",
     "referenceType": "cpe23Type",
     "referenceLocator": "cpe:2.3:a:src-d:gcfg:v1.4.0:*:*:*:*:*:*:*",
     "comment": ""
    },
    {
     "referenceCategory": "SECURITY",
     "referenceType": "cpe23Type",
     "referenceLocator": "cpe:2.3:a:src_d:gcfg:v1.4.0:*:*:*:*:*:*:*",
     "comment": ""
    },
    {
     "referenceCategory": "SECURITY",
     "referenceType": "cpe23Type",
     "referenceLocator": "cpe:2.3:a:src:gcfg:v1.4.0:*:*:*:*:*:*:*",
     "comment": ""
    },
    {
     "referenceCategory": "PACKAGE-MANAGER",
     "referenceType": "purl",
     "referenceLocator": "pkg:golang/github.com/src-d/gcfg@v1.4.0",
     "comment": ""
    }
   ]
  },
  {
   "name": "github.com/tomasen/realip",
   "SPDXID": "SPDXRef-Package-go-module-github.com-tomasen-realip-6ff4cd5c3f963528",
   "versionInfo": "v0.0.0-20180522021738-f0c99a92ddce",
   "downloadLocation": "NOASSERTION",
   "checksums": [
    {
     "algorithm": "SHA256",
     "checksumValue": "7dbd7dd3e70ad97cff76f8bd1eff1e098258bc81944cddbf28bab5a53e828c47"
    }
   ],
   "sourceInfo": "acquired package info from go module information: /portainer",
   "licenseConcluded": "NONE",
   "licenseDeclared": "NONE",
   "copyrightText": "NOASSERTION",
   "externalRefs": [
    {
     "referenceCategory": "SECURITY",
     "referenceType": "cpe23Type",
     "referenceLocator": "cpe:2.3:a:tomasen:realip:v0.0.0-20180522021738-f0c99a92ddce:*:*:*:*:*:*:*",
     "comment": ""
    },
    {
     "referenceCategory": "PACKAGE-MANAGER",
     "referenceType": "purl",
     "referenceLocator": "pkg:golang/github.com/tomasen/realip@v0.0.0-20180522021738-f0c99a92ddce",
     "comment": ""
    }
   ]
  },
  {
   "name": "github.com/xanzy/ssh-agent",
   "SPDXID": "SPDXRef-Package-go-module-github.com-xanzy-ssh-agent-26c974cdab27fabf",
   "versionInfo": "v0.2.1",
   "downloadLocation": "NOASSERTION",
   "checksums": [
    {
     "algorithm": "SHA256",
     "checksumValue": "4c26e2a5340bd898a20a9ac15b1f5fac9d9e2650984f4d0d99cb6b1f1540afbd"
    }
   ],
   "sourceInfo": "acquired package info from go module information: /portainer",
   "licenseConcluded": "NONE",
   "licenseDeclared": "NONE",
   "copyrightText": "NOASSERTION",
   "externalRefs": [
    {
     "referenceCategory": "SECURITY",
     "referenceType": "cpe23Type",
     "referenceLocator": "cpe:2.3:a:xanzy:ssh-agent:v0.2.1:*:*:*:*:*:*:*",
     "comment": ""
    },
    {
     "referenceCategory": "SECURITY",
     "referenceType": "cpe23Type",
     "referenceLocator": "cpe:2.3:a:xanzy:ssh_agent:v0.2.1:*:*:*:*:*:*:*",
     "comment": ""
    },
    {
     "referenceCategory": "PACKAGE-MANAGER",
     "referenceType": "purl",
     "referenceLocator": "pkg:golang/github.com/xanzy/ssh-agent@v0.2.1",
     "comment": ""
    }
   ]
  },
  {
   "name": "github.com/xeipuuv/gojsonpointer",
   "SPDXID": "SPDXRef-Package-go-module-github.com-xeipuuv-gojsonpointer-a65bc958ab4115bd",
   "versionInfo": "v0.0.0-20180127040702-4e3ac2762d5f",
   "downloadLocation": "NOASSERTION",
   "checksums": [
    {
     "algorithm": "SHA256",
     "checksumValue": "27d106a5c66d3f413fadaa2b08cc6514649306bb1295a0c67f78d4feabc01367"
    }
   ],
   "sourceInfo": "acquired package info from go module information: /portainer",
   "licenseConcluded": "NONE",
   "licenseDeclared": "NONE",
   "copyrightText": "NOASSERTION",
   "externalRefs": [
    {
     "referenceCategory": "SECURITY",
     "referenceType": "cpe23Type",
     "referenceLocator": "cpe:2.3:a:xeipuuv:gojsonpointer:v0.0.0-20180127040702-4e3ac2762d5f:*:*:*:*:*:*:*",
     "comment": ""
    },
    {
     "referenceCategory": "PACKAGE-MANAGER",
     "referenceType": "purl",
     "referenceLocator": "pkg:golang/github.com/xeipuuv/gojsonpointer@v0.0.0-20180127040702-4e3ac2762d5f",
     "comment": ""
    }
   ]
  },
  {
   "name": "github.com/xeipuuv/gojsonreference",
   "SPDXID": "SPDXRef-Package-go-module-github.com-xeipuuv-gojsonreference-572903ad3bd3571b",
   "versionInfo": "v0.0.0-20180127040603-bd5ef7bd5415",
   "downloadLocation": "NOASSERTION",
   "checksums": [
    {
     "algorithm": "SHA256",
     "checksumValue": "133256807a2fa27b7b36c723a40c57b0303c4bc04c62f7bc639fbb72e444ed1d"
    }
   ],
   "sourceInfo": "acquired package info from go module information: /portainer",
   "licenseConcluded": "NONE",
   "licenseDeclared": "NONE",
   "copyrightText": "NOASSERTION",
   "externalRefs": [
    {
     "referenceCategory": "SECURITY",
     "referenceType": "cpe23Type",
     "referenceLocator": "cpe:2.3:a:xeipuuv:gojsonreference:v0.0.0-20180127040603-bd5ef7bd5415:*:*:*:*:*:*:*",
     "comment": ""
    },
    {
     "referenceCategory": "PACKAGE-MANAGER",
     "referenceType": "purl",
     "referenceLocator": "pkg:golang/github.com/xeipuuv/gojsonreference@v0.0.0-20180127040603-bd5ef7bd5415",
     "comment": ""
    }
   ]
  },
  {
   "name": "github.com/xeipuuv/gojsonschema",
   "SPDXID": "SPDXRef-Package-go-module-github.com-xeipuuv-gojsonschema-2466feb75f151130",
   "versionInfo": "v1.1.0",
   "downloadLocation": "NOASSERTION",
   "checksums": [
    {
     "algorithm": "SHA256",
     "checksumValue": "9e056d242f5363f960d0003fd64e3c158841ae14681651265b3b1e8693406998"
    }
   ],
   "sourceInfo": "acquired package info from go module information: /portainer",
   "licenseConcluded": "NONE",
   "licenseDeclared": "NONE",
   "copyrightText": "NOASSERTION",
   "externalRefs": [
    {
     "referenceCategory": "SECURITY",
     "referenceType": "cpe23Type",
     "referenceLocator": "cpe:2.3:a:xeipuuv:gojsonschema:v1.1.0:*:*:*:*:*:*:*",
     "comment": ""
    },
    {
     "referenceCategory": "PACKAGE-MANAGER",
     "referenceType": "purl",
     "referenceLocator": "pkg:golang/github.com/xeipuuv/gojsonschema@v1.1.0",
     "comment": ""
    }
   ]
  },
  {
   "name": "golang.org/x/crypto",
   "SPDXID": "SPDXRef-Package-go-module-golang.org-x-crypto-a14b3a29b9811328",
   "versionInfo": "v0.0.0-20191128160524-b544559bb6d1",
   "downloadLocation": "NOASSERTION",
   "checksums": [
    {
     "algorithm": "SHA256",
     "checksumValue": "6a7192610a4f850c17970b2ee7099fab49d690235a304314c00bf5dd8f7685df"
    }
   ],
   "sourceInfo": "acquired package info from go module information: /portainer",
   "licenseConcluded": "NONE",
   "licenseDeclared": "NONE",
   "copyrightText": "NOASSERTION",
   "externalRefs": [
    {
     "referenceCategory": "SECURITY",
     "referenceType": "cpe23Type",
     "referenceLocator": "cpe:2.3:a:golang:x\\/crypto:v0.0.0-20191128160524-b544559bb6d1:*:*:*:*:*:*:*",
     "comment": ""
    },
    {
     "referenceCategory": "PACKAGE-MANAGER",
     "referenceType": "purl",
     "referenceLocator": "pkg:golang/golang.org/x/crypto@v0.0.0-20191128160524-b544559bb6d1",
     "comment": ""
    }
   ]
  },
  {
   "name": "golang.org/x/net",
   "SPDXID": "SPDXRef-Package-go-module-golang.org-x-net-4d112f090b3d970b",
   "versionInfo": "v0.0.0-20191126235420-ef20fe5d7933",
   "downloadLocation": "NOASSERTION",
   "checksums": [
    {
     "algorithm": "SHA256",
     "checksumValue": "7ba1f08a35318437be84f363650427f5b0393d6def3669cdeb8536656ef9f4b9"
    }
   ],
   "sourceInfo": "acquired package info from go module information: /portainer",
   "licenseConcluded": "NONE",
   "licenseDeclared": "NONE",
   "copyrightText": "NOASSERTION",
   "externalRefs": [
    {
     "referenceCategory": "SECURITY",
     "referenceType": "cpe23Type",
     "referenceLocator": "cpe:2.3:a:golang:x\\/net:v0.0.0-20191126235420-ef20fe5d7933:*:*:*:*:*:*:*",
     "comment": ""
    },
    {
     "referenceCategory": "PACKAGE-MANAGER",
     "referenceType": "purl",
     "referenceLocator": "pkg:golang/golang.org/x/net@v0.0.0-20191126235420-ef20fe5d7933",
     "comment": ""
    }
   ]
  },
  {
   "name": "golang.org/x/oauth2",
   "SPDXID": "SPDXRef-Package-go-module-golang.org-x-oauth2-61ef276a17a904a0",
   "versionInfo": "v0.0.0-20190604053449-0f29369cfe45",
   "downloadLocation": "NOASSERTION",
   "checksums": [
    {
     "algorithm": "SHA256",
     "checksumValue": "495c1320068f0b653f02fbcb359d9aece56c981a42f0be419702b5c211f7866d"
    }
   ],
   "sourceInfo": "acquired package info from go module information: /portainer",
   "licenseConcluded": "NONE",
   "licenseDeclared": "NONE",
   "copyrightText": "NOASSERTION",
   "externalRefs": [
    {
     "referenceCategory": "SECURITY",
     "referenceType": "cpe23Type",
     "referenceLocator": "cpe:2.3:a:golang:x\\/oauth2:v0.0.0-20190604053449-0f29369cfe45:*:*:*:*:*:*:*",
     "comment": ""
    },
    {
     "referenceCategory": "PACKAGE-MANAGER",
     "referenceType": "purl",
     "referenceLocator": "pkg:golang/golang.org/x/oauth2@v0.0.0-20190604053449-0f29369cfe45",
     "comment": ""
    }
   ]
  },
  {
   "name": "golang.org/x/sync",
   "SPDXID": "SPDXRef-Package-go-module-golang.org-x-sync-15a4b07dae552e67",
   "versionInfo": "v0.0.0-20190423024810-112230192c58",
   "downloadLocation": "NOASSERTION",
   "checksums": [
    {
     "algorithm": "SHA256",
     "checksumValue": "f20415e822e70048a4ae18241c56cc00485a8124a75d6195f75e6a50c9bd9ab5"
    }
   ],
   "sourceInfo": "acquired package info from go module information: /portainer",
   "licenseConcluded": "NONE",
   "licenseDeclared": "NONE",
   "copyrightText": "NOASSERTION",
   "externalRefs": [
    {
     "referenceCategory": "SECURITY",
     "referenceType": "cpe23Type",
     "referenceLocator": "cpe:2.3:a:golang:x\\/sync:v0.0.0-20190423024810-112230192c58:*:*:*:*:*:*:*",
     "comment": ""
    },
    {
     "referenceCategory": "PACKAGE-MANAGER",
     "referenceType": "purl",
     "referenceLocator": "pkg:golang/golang.org/x/sync@v0.0.0-20190423024810-112230192c58",
     "comment": ""
    }
   ]
  },
  {
   "name": "golang.org/x/sys",
   "SPDXID": "SPDXRef-Package-go-module-golang.org-x-sys-fc8b9d4ce56dcd53",
   "versionInfo": "v0.0.0-20190826190057-c7b8b68b1456",
   "downloadLocation": "NOASSERTION",
   "checksums": [
    {
     "algorithm": "SHA256",
     "checksumValue": "9e0d20b3500a9d146e10c6684cb2e56ce77e0b5ef35037a9c064016ff9fe2558"
    }
   ],
   "sourceInfo": "acquired package info from go module information: /portainer",
   "licenseConcluded": "NONE",
   "licenseDeclared": "NONE",
   "copyrightText": "NOASSERTION",
   "externalRefs": [
    {
     "referenceCategory": "SECURITY",
     "referenceType": "cpe23Type",
     "referenceLocator": "cpe:2.3:a:golang:x\\/sys:v0.0.0-20190826190057-c7b8b68b1456:*:*:*:*:*:*:*",
     "comment": ""
    },
    {
     "referenceCategory": "PACKAGE-MANAGER",
     "referenceType": "purl",
     "referenceLocator": "pkg:golang/golang.org/x/sys@v0.0.0-20190826190057-c7b8b68b1456",
     "comment": ""
    }
   ]
  },
  {
   "name": "golang.org/x/text",
   "SPDXID": "SPDXRef-Package-go-module-golang.org-x-text-50fccfd23dc3822d",
   "versionInfo": "v0.3.2",
   "downloadLocation": "NOASSERTION",
   "checksums": [
    {
     "algorithm": "SHA256",
     "checksumValue": "b56d9b9a206ac20263fd4a6ab42f04a571195583b0534c86e2259ba6b49501cb"
    }
   ],
   "sourceInfo": "acquired package info from go module information: /portainer",
   "licenseConcluded": "NONE",
   "licenseDeclared": "NONE",
   "copyrightText": "NOASSERTION",
   "externalRefs": [
    {
     "referenceCategory": "SECURITY",
     "referenceType": "cpe23Type",
     "referenceLocator": "cpe:2.3:a:golang:x\\/text:v0.3.2:*:*:*:*:*:*:*",
     "comment": ""
    },
    {
     "referenceCategory": "PACKAGE-MANAGER",
     "referenceType": "purl",
     "referenceLocator": "pkg:golang/golang.org/x/text@v0.3.2",
     "comment": ""
    }
   ]
  },
  {
   "name": "golang.org/x/time",
   "SPDXID": "SPDXRef-Package-go-module-golang.org-x-time-f5b8dcff6235bd99",
   "versionInfo": "v0.0.0-20190308202827-9d24e82272b4",
   "downloadLocation": "NOASSERTION",
   "checksums": [
    {
     "algorithm": "SHA256",
     "checksumValue": "4af1594fa8f2a9168e797a5ce61fc949f65e9c9d8edf7d1a06c7fb25f4945e64"
    }
   ],
   "sourceInfo": "acquired package info from go module information: /portainer",
   "licenseConcluded": "NONE",
   "licenseDeclared": "NONE",
   "copyrightText": "NOASSERTION",
   "externalRefs": [
    {
     "referenceCategory": "SECURITY",
     "referenceType": "cpe23Type",
     "referenceLocator": "cpe:2.3:a:golang:x\\/time:v0.0.0-20190308202827-9d24e82272b4:*:*:*:*:*:*:*",
     "comment": ""
    },
    {
     "referenceCategory": "PACKAGE-MANAGER",
     "referenceType": "purl",
     "referenceLocator": "pkg:golang/golang.org/x/time@v0.0.0-20190308202827-9d24e82272b4",
     "comment": ""
    }
   ]
  },
  {
   "name": "google.golang.org/genproto",
   "SPDXID": "SPDXRef-Package-go-module-google.golang.org-genproto-94517736baf57614",
   "versionInfo": "v0.0.0-20190418145605-e7d98fc518a7",
   "downloadLocation": "NOASSERTION",
   "checksums": [
    {
     "algorithm": "SHA256",
     "checksumValue": "6548d70179ab032ae69823c780203fbc2847729b17dbb319df20689c3ff3d4a1"
    }
   ],
   "sourceInfo": "acquired package info from go module information: /portainer",
   "licenseConcluded": "NONE",
   "licenseDeclared": "NONE",
   "copyrightText": "NOASSERTION",
   "externalRefs": [
    {
     "referenceCategory": "SECURITY",
     "referenceType": "cpe23Type",
     "referenceLocator": "cpe:2.3:a:google:genproto:v0.0.0-20190418145605-e7d98fc518a7:*:*:*:*:*:*:*",
     "comment": ""
    },
    {
     "referenceCategory": "PACKAGE-MANAGER",
     "referenceType": "purl",
     "referenceLocator": "pkg:golang/google.golang.org/genproto@v0.0.0-20190418145605-e7d98fc518a7",
     "comment": ""
    }
   ]
  },
  {
   "name": "google.golang.org/grpc",
   "SPDXID": "SPDXRef-Package-go-module-google.golang.org-grpc-f4838297ea6069b0",
   "versionInfo": "v1.22.1",
   "downloadLocation": "NOASSERTION",
   "checksums": [
    {
     "algorithm": "SHA256",
     "checksumValue": "ffb72ce764674c9983e37b37bb1ce5ab653b9ea55377fdfbbe243032b30d94e3"
    }
   ],
   "sourceInfo": "acquired package info from go module information: /portainer",
   "licenseConcluded": "NONE",
   "licenseDeclared": "NONE",
   "copyrightText": "NOASSERTION",
   "externalRefs": [
    {
     "referenceCategory": "SECURITY",
     "referenceType": "cpe23Type",
     "referenceLocator": "cpe:2.3:a:google:grpc:v1.22.1:*:*:*:*:*:*:*",
     "comment": ""
    },
    {
     "referenceCategory": "PACKAGE-MANAGER",
     "referenceType": "purl",
     "referenceLocator": "pkg:golang/google.golang.org/grpc@v1.22.1",
     "comment": ""
    }
   ]
  },
  {
   "name": "gopkg.in/alecthomas/kingpin.v2",
   "SPDXID": "SPDXRef-Package-go-module-gopkg.in-alecthomas-kingpin.v2-4eec7d27f41c73f5",
   "versionInfo": "v2.2.6",
   "downloadLocation": "NOASSERTION",
   "checksums": [
    {
     "algorithm": "SHA256",
     "checksumValue": "8cc173e8c7cb3f4ff87d4c9995ef35ad7528c4e0458b5f555052950ce41fa337"
    }
   ],
   "sourceInfo": "acquired package info from go module information: /portainer",
   "licenseConcluded": "NONE",
   "licenseDeclared": "NONE",
   "copyrightText": "NOASSERTION",
   "externalRefs": [
    {
     "referenceCategory": "PACKAGE-MANAGER",
     "referenceType": "purl",
     "referenceLocator": "pkg:golang/gopkg.in/alecthomas/kingpin.v2@v2.2.6",
     "comment": ""
    }
   ]
  },
  {
   "name": "gopkg.in/inf.v0",
   "SPDXID": "SPDXRef-Package-go-module-gopkg.in-inf.v0-90b6c1c05bc9ab6",
   "versionInfo": "v0.9.1",
   "downloadLocation": "NOASSERTION",
   "checksums": [
    {
     "algorithm": "SHA256",
     "checksumValue": "ef73390a86728b764b30ec83950874df50b1e8df4d0c9d95bdf97be840c08037"
    }
   ],
   "sourceInfo": "acquired package info from go module information: /portainer",
   "licenseConcluded": "NONE",
   "licenseDeclared": "NONE",
   "copyrightText": "NOASSERTION",
   "externalRefs": [
    {
     "referenceCategory": "PACKAGE-MANAGER",
     "referenceType": "purl",
     "referenceLocator": "pkg:golang/gopkg.in/inf.v0@v0.9.1",
     "comment": ""
    }
   ]
  },
  {
   "name": "gopkg.in/ldap.v2",
   "SPDXID": "SPDXRef-Package-go-module-gopkg.in-ldap.v2-9ad7ca79de223d7f",
   "versionInfo": "v2.5.1",
   "downloadLocation": "NOASSERTION",
   "checksums": [
    {
     "algorithm": "SHA256",
     "checksumValue": "c22bb4a2474d7e3941ce0e945af7751e7f18f94c75effbbfe27964e0242bead5"
    }
   ],
   "sourceInfo": "acquired package info from go module information: /portainer",
   "licenseConcluded": "NONE",
   "licenseDeclared": "NONE",
   "copyrightText": "NOASSERTION",
   "externalRefs": [
    {
     "referenceCategory": "PACKAGE-MANAGER",
     "referenceType": "purl",
     "referenceLocator": "pkg:golang/gopkg.in/ldap.v2@v2.5.1",
     "comment": ""
    }
   ]
  },
  {
   "name": "gopkg.in/src-d/go-billy.v4",
   "SPDXID": "SPDXRef-Package-go-module-gopkg.in-src-d-go-billy.v4-e57310bde77b2d14",
   "versionInfo": "v4.3.2",
   "downloadLocation": "NOASSERTION",
   "checksums": [
    {
     "algorithm": "SHA256",
     "checksumValue": "d12400d69473b5f4c5c769a24bcb00f7b5efa2815e34e9af51e9c5e28d047158"
    }
   ],
   "sourceInfo": "acquired package info from go module information: /portainer",
   "licenseConcluded": "NONE",
   "licenseDeclared": "NONE",
   "copyrightText": "NOASSERTION",
   "externalRefs": [
    {
     "referenceCategory": "PACKAGE-MANAGER",
     "referenceType": "purl",
     "referenceLocator": "pkg:golang/gopkg.in/src-d/go-billy.v4@v4.3.2",
     "comment": ""
    }
   ]
  },
  {
   "name": "gopkg.in/src-d/go-git.v4",
   "SPDXID": "SPDXRef-Package-go-module-gopkg.in-src-d-go-git.v4-673cf8785ece81de",
   "versionInfo": "v4.13.1",
   "downloadLocation": "NOASSERTION",
   "checksums": [
    {
     "algorithm": "SHA256",
     "checksumValue": "491b45c95f0ac5cd143fb6821dc8a338c4063f11d298c38faf3ba5416a259181"
    }
   ],
   "sourceInfo": "acquired package info from go module information: /portainer",
   "licenseConcluded": "NONE",
   "licenseDeclared": "NONE",
   "copyrightText": "NOASSERTION",
   "externalRefs": [
    {
     "referenceCategory": "PACKAGE-MANAGER",
     "referenceType": "purl",
     "referenceLocator": "pkg:golang/gopkg.in/src-d/go-git.v4@v4.13.1",
     "comment": ""
    }
   ]
  },
  {
   "name": "gopkg.in/warnings.v0",
   "SPDXID": "SPDXRef-Package-go-module-gopkg.in-warnings.v0-9befc2dcd6b4523b",
   "versionInfo": "v0.1.2",
   "downloadLocation": "NOASSERTION",
   "checksums": [
    {
     "algorithm": "SHA256",
     "checksumValue": "c055d56c563c0d8e7fc4e7b510289674a0b3665c60b2171854d9011ecb4044c1"
    }
   ],
   "sourceInfo": "acquired package info from go module information: /portainer",
   "licenseConcluded": "NONE",
   "licenseDeclared": "NONE",
   "copyrightText": "NOASSERTION",
   "externalRefs": [
    {
     "referenceCategory": "PACKAGE-MANAGER",
     "referenceType": "purl",
     "referenceLocator": "pkg:golang/gopkg.in/warnings.v0@v0.1.2",
     "comment": ""
    }
   ]
  },
  {
   "name": "gopkg.in/yaml.v2",
   "SPDXID": "SPDXRef-Package-go-module-gopkg.in-yaml.v2-c394faa6264ccb8e",
   "versionInfo": "v2.2.4",
   "downloadLocation": "NOASSERTION",
   "checksums": [
    {
     "algorithm": "SHA256",
     "checksumValue": "fde889ad472e8cf55e277c654966a2362dee4959831812b5a431d41c09daa352"
    }
   ],
   "sourceInfo": "acquired package info from go module information: /portainer",
   "licenseConcluded": "NONE",
   "licenseDeclared": "NONE",
   "copyrightText": "NOASSERTION",
   "externalRefs": [
    {
     "referenceCategory": "PACKAGE-MANAGER",
     "referenceType": "purl",
     "referenceLocator": "pkg:golang/gopkg.in/yaml.v2@v2.2.4",
     "comment": ""
    }
   ]
  },
  {
   "name": "k8s.io/api",
   "SPDXID": "SPDXRef-Package-go-module-k8s.io-api-96dacde2b7a0b327",
   "versionInfo": "v0.17.2",
   "downloadLocation": "NOASSERTION",
   "checksums": [
    {
     "algorithm": "SHA256",
     "checksumValue": "345d5415770a37bfce3afd6ec5d473dea7eb6bc007b0f6afe4cf7786557df837"
    }
   ],
   "sourceInfo": "acquired package info from go module information: /portainer",
   "licenseConcluded": "NONE",
   "licenseDeclared": "NONE",
   "copyrightText": "NOASSERTION",
   "externalRefs": [
    {
     "referenceCategory": "PACKAGE-MANAGER",
     "referenceType": "purl",
     "referenceLocator": "pkg:golang/k8s.io/api@v0.17.2",
     "comment": ""
    }
   ]
  },
  {
   "name": "k8s.io/apimachinery",
   "SPDXID": "SPDXRef-Package-go-module-k8s.io-apimachinery-c8c094713cf26257",
   "versionInfo": "v0.17.2",
   "downloadLocation": "NOASSERTION",
   "checksums": [
    {
     "algorithm": "SHA256",
     "checksumValue": "8700d04056dd465a679ec47ae00b1d8b9e46c826883ffdd64293266cd05e5abe"
    }
   ],
   "sourceInfo": "acquired package info from go module information: /portainer",
   "licenseConcluded": "NONE",
   "licenseDeclared": "NONE",
   "copyrightText": "NOASSERTION",
   "externalRefs": [
    {
     "referenceCategory": "PACKAGE-MANAGER",
     "referenceType": "purl",
     "referenceLocator": "pkg:golang/k8s.io/apimachinery@v0.17.2",
     "comment": ""
    }
   ]
  },
  {
   "name": "k8s.io/client-go",
   "SPDXID": "SPDXRef-Package-go-module-k8s.io-client-go-25a5a923ead9b238",
   "versionInfo": "v0.17.2",
   "downloadLocation": "NOASSERTION",
   "checksums": [
    {
     "algorithm": "SHA256",
     "checksumValue": "9dd21f91f5c41ab3612c8824af4faa85182e483deee830a6a277a99f53ba3587"
    }
   ],
   "sourceInfo": "acquired package info from go module information: /portainer",
   "licenseConcluded": "NONE",
   "licenseDeclared": "NONE",
   "copyrightText": "NOASSERTION",
   "externalRefs": [
    {
     "referenceCategory": "PACKAGE-MANAGER",
     "referenceType": "purl",
     "referenceLocator": "pkg:golang/k8s.io/client-go@v0.17.2",
     "comment": ""
    }
   ]
  },
  {
   "name": "k8s.io/klog",
   "SPDXID": "SPDXRef-Package-go-module-k8s.io-klog-e30d44cfd15d5b67",
   "versionInfo": "v1.0.0",
   "downloadLocation": "NOASSERTION",
   "checksums": [
    {
     "algorithm": "SHA256",
     "checksumValue": "3edfb28c5e5a075c434956dabb856c59ef9d40dcc0d2abf52e55dd0b6745e90f"
    }
   ],
   "sourceInfo": "acquired package info from go module information: /portainer",
   "licenseConcluded": "NONE",
   "licenseDeclared": "NONE",
   "copyrightText": "NOASSERTION",
   "externalRefs": [
    {
     "referenceCategory": "PACKAGE-MANAGER",
     "referenceType": "purl",
     "referenceLocator": "pkg:golang/k8s.io/klog@v1.0.0",
     "comment": ""
    }
   ]
  },
  {
   "name": "k8s.io/utils",
   "SPDXID": "SPDXRef-Package-go-module-k8s.io-utils-cfa24975486a983d",
   "versionInfo": "v0.0.0-20191114184206-e782cd3c129f",
   "downloadLocation": "NOASSERTION",
   "checksums": [
    {
     "algorithm": "SHA256",
     "checksumValue": "1a23f0b52cdd3f8dde2358693c26d13900822200ae88c30d17c61454b177bc9a"
    }
   ],
   "sourceInfo": "acquired package info from go module information: /portainer",
   "licenseConcluded": "NONE",
   "licenseDeclared": "NONE",
   "copyrightText": "NOASSERTION",
   "externalRefs": [
    {
     "referenceCategory": "PACKAGE-MANAGER",
     "referenceType": "purl",
     "referenceLocator": "pkg:golang/k8s.io/utils@v0.0.0-20191114184206-e782cd3c129f",
     "comment": ""
    }
   ]
  },
  {
   "name": "sigs.k8s.io/yaml",
   "SPDXID": "SPDXRef-Package-go-module-sigs.k8s.io-yaml-d2e77ac0ca86bba3",
   "versionInfo": "v1.1.0",
   "downloadLocation": "NOASSERTION",
   "checksums": [
    {
     "algorithm": "SHA256",
     "checksumValue": "e00d3bf9915cdb0809c28f18365429af5ad59605039715c784f25c89a3d8e60b"
    }
   ],
   "sourceInfo": "acquired package info from go module information: /portainer",
   "licenseConcluded": "NONE",
   "licenseDeclared": "NONE",
   "copyrightText": "NOASSERTION",
   "externalRefs": [
    {
     "referenceCategory": "PACKAGE-MANAGER",
     "referenceType": "purl",
     "referenceLocator": "pkg:golang/sigs.k8s.io/yaml@v1.1.0",
     "comment": ""
    }
   ]
  }
 ],
 "relationships": [
  {
   "spdxElementId": "SPDXRef-DOCUMENT",
   "relatedSpdxElement": "SPDXRef-DOCUMENT",
   "relationshipType": "DESCRIBES"
  }
 ]
}
